Workbook

Sheet PORTADA
A25: CAJA DE AHORRO
A26: CAJA DE AHORRO
A27: COMUNAL VERDECOCHA
A28: Sembrando juntos para un futuro
B30: GESTIÓN DE SOCIOS | K30: CALCULOS Y RESULTADOS | T30: MOVIMIENTO FINANCIERO

Sheet CUERPO DIRECTIVO

Sheet CUERPO NORMATIVO
H1: CAJA DE AHORRO
H4: COMUNAL
H6: VERDECOCHA
H8: Sembrando juntos para un futuro
A10: CUERPO NORMATIVO

Sheet LISTADO DE SOCIOS
C2: CAJA DE AHORRO
C4: COMUNAL
C5: VERDECOCHA
C6: Sembrando juntos para un futuro
B8: NÓMINA DE SOCIOS
B10: No. | C10: NÓMINA | D10: N. CEDULA | E10: N. TELEFONO | F10: MES DE INGRESO | G10: AHORRO MENSUAL
B11: 1 | C11: ALVAREZ PRUNA LUIS HERIBERTO | D11: 0501066443 | E11: 984545786 | F11: JUNIO | G11: 5
B12: 2 | C12: CHACHAPOYA TOAPANTA RAUL GERARDO | D12: 0502321714 | E12: 968863419 | F12: JUNIO | G12: 5
B13: 3 | C13: CHICAIZA CHACON GLORIA MARINA | D13: 0501425441 | E13: 91563213 | F13: JUNIO | G13: 5
B14: 4 | C14: HERRERA ZAPATA CARMEN ALICIA | D14: 0502277353 | E14: 999123059 | F14: JUNIO | G14: 5
B15: 5 | C15: HERRERA ZAPATA ELSA PIEDAD | D15: 0500953344 | E15: 997382721 | F15: JUNIO | G15: 5
B16: 6 | C16: HERRERA HERRERA JOANA ALEXANDRA | D16: 0502659931 | E16: 990859733 | F16: JUNIO | G16: 5
B17: 7 | C17: MOLINA BELTRAN LUIS RAFAEL | D17: 0503026213 | E17: 987740310 | F17: SEPTIEMBRE | G17: 15
B18: 8 | C18: MONGE PRUNA JOSUE DAMIÁN | D18: 0550368096 | E18: 995099733 | F18: JUNIO | G18: 5
B19: 9 | C19: MOSCUY ALVAREZ ANTONY ALEXANDER | D19: 0550140743 | E19: 999049833 | F19: AGOSTO | G19: 10
B20: 10 | C20: MOSCUY ALVAREZ MONICA AZUCENA | D20: 0504024654 | E20: 998875280 | F20: JUNIO | G20: 5
B21: 11 | C21: MOSCUY CULQUI MARIA NORMA | D21: 0502275407 | E21: 983005533 | F21: JUNIO | G21: 5
B22: 12 | C22: MOSCUY ALVAREZ BLANCA ROCIO | D22: 0502524226 | E22: 978726903 | F22: AGOSTO | G22: 5
... B35: 25 | C35: ZAPATA HERRERA ALEX DAVID | D35: 2200613137 | E35: 980246048 | F35: JUNIO | G35: 5
B36: TOTAL | G36: =SUM(G11:G35) -> 150

Sheet REGISTRO CONTABLE
B1: C
B2: CAJA DE AHORRO
B4: COMUNAL
B5: VERDECOCHA
B6: Sembrando juntos para un futuro
B8: REUNION | C8: REGISTRO CONTABLE
C9: FECHA | D9: DESCRIPCION | E9: CAJA | G9: SALDOS
E10: ENTRADA | F10: SALIDA | G10: CAJA
B11: 1 | C11: 45472 | D11: Aporte inicial (Rifa) | E11: 200 | G11: =E11 -> 200
B12: 1 | C12: 45472 | D12: Credito veronica sinchiguano | F12: 100 | G12: =G11+E12-F12 -> 100
B13: 1 | C13: 45502 | D13: Aporte inicial Juan Pruna/Miriam Rodriguez | E13: 20 | G13: =G12+E13-F13 -> 120
B14: 2 | C14: 45499 | D14: Aporte inicial | E14: 100 | G14: =G13+E14-F14 -> 220
B15: 2 | C15: 45499 | D15: interes cobrado | E15: 5 | G15: =G14+E15-F15 -> 225
B16: 2 | C16: 45499 | D16: Credito concedido Carmen Herrera | F16: 100 | G16: =G15+E16-F16 -> 125
B17: 2 | C17: 45499 | D17: Credito concedido Carlos Peñafiel | F17: 100 | G17: =G16+E17-F17 -> 25
B18: 3 | C18: 45534 | D18: Ingreso de ahorros | E18: 125 | G18: =G17+E18-F18 -> 150
B19: 3 | C19: 45534 | D19: Aporte inicial Rocio / Antoni Moscuy | E19: 20 | G19: =G18+E19-F19 -> 170
B20: 3 | C20: 45534 | D20: interes cobrado | E20: 15 | G20: =G19+E20-F20 -> 185
B21: 3 | C21: 45534 | D21: Credito concedido | F21: 100 | G21: =G20+E21-F21 -> 85
B22: 3 | C22: 45534 | D22: Credito concedido | F22: 100 | G22: =G21+E22-F22 -> -15
B23: 3 | C23: 45562 | D23: Ingresos ahorro | E23: 145 | G23: =G22+E23-F23 -> 130
B24: 4 | C24: 45562 | D24: aporte inicial | E24: 20 | G24: =G23+E24-F24 -> 150
B25: 4 | C25: 45562 | D25: interes cobrado | E25: 25 | G25: =G24+E25-F25 -> 175
B26: 4 | C26: 45562 | D26: Pago capital (veronica Sinchiguano) | E26: 100 | G26: =G25+E26-F26 -> 275
B27: 4 | C27: 45562 | D27: Credito concedido | F27: 100 | G27: =G26+E27-F27 -> 175
B28: 4 | C28: 45562 | D28: Credito concedido | F28: 100 | G28: =G27+E28-F28 -> 75
B29: 4 | C29: 45562 | D29: Credito concedido | F29: 100 | G29: =G28+E29-F29 -> -25
B30: 5 | C30: 45589 | D30: Ingreso ahorro | E30: 125 | G30: =G29+E30-F30 -> 100
B31: 5 | C31: 45589 | D31: pago capital (Carmen Herrera) | E31: 100 | G31: =G30+E31-F31 -> 200
B32: 5 | C32: 45589 | D32: pago capital (Carlos Peñafiel) | E32: 100 | G32: =G31+E32-F32 -> 300
B33: 5 | C33: 45589 | D33: interes cobrado | E33: 35 | G33: =G32+E33-F33 -> 335 | H33: =+SUM(E31:E33) -> 235
B34: 5 | C34: 45589 | D34: Credito Antony Moscuy | F34: 100 | G34: =G33+E34-F34 -> 235
B35: 5 | C35: 45589 | D35: Credito Carmen Herrera | F35: 180 | G35: =G34+E35-F35 -> 55
B36: 5 | C36: 45589 | D36: Credito Peñafiel Carlos | F36: 100 | G36: =G35+E36-F36 -> -45
B37: 6 | C37: 45625 | D37: Ingreso ahorro | E37: 125 | G37: =G36+E37-F37 -> 80
B38: 6 | C38: 45625 | D38: pago capital (Rocio Moscuy) | E38: 100 | G38: =G37+E38-F38 -> 180
B39: 6 | C39: 45625 | D39: pago capital (Norma Pruna) | E39: 100 | G39: =G38+E39-F39 -> 280
B40: 6 | C40: 45625 | D40: interes cobrado | E40: 44 | G40: =G39+E40-F40 -> 324 | H40: =+SUM(E38:E40) -> 244
B41: 6 | C41: 45625 | D41: Credito Rocio Moscuy | F41: 200 | G41: =G40+E41-F41 -> 124
B42: 6 | C42: 45625 | D42: Credito Norma Pruna | F42: 100 | G42: =G41+E42-F42 -> 24
B43: 6 | C43: 45625 | D43: credito Herrera Joana | F43: 80 | G43: =G42+E43-F43 -> -56
B44: 7 | C44: 45653 | D44: Ingreso ahorro | E44: 125 | G44: =G43+E44-F44 -> 69
B45: 7 | C45: 45653 | D45: pago capital (Joana Herrera) | E45: 100 | G45: =G44+E45-F45 -> 169
B46: 7 | C46: 45653 | D46: pago capital (Norma Moscuy) | E46: 100 | G46: =G45+E46-F46 -> 269
B47: 7 | C47: 45653 | D47: pago capital (Veronica sinchiguano) | E47: 100 | G47: =G46+E47-F47 -> 369
B48: 7 | C48: 45653 | D48: interes cobrado | E48: 53 | G48: =G47+E48-F48 -> 422 | H48: =+SUM(E45:E48) -> 353
B49: 7 | C49: 45653 | D49: Credito Lizardo Pruna | F49: 200 | G49: =G48+E49-F49 -> 222
B50: 7 | C50: 45653 | D50: Credito Alex Zapata | F50: 200 | G50: =G49+E50-F50 -> 22
B51: 8 | C51: 45688 | D51: Ingreso ahorro | E51: 125 | G51: =G50+E51-F51 -> 147
B52: 8 | C52: 45688 | D52: pago capital (Carmen Herrera) | E52: 180 | G52: =G51+E52-F52 -> 327
B53: 8 | C53: 45688 | D53: pago capital (Anthony Moscuy) | E53: 100 | G53: =G52+E53-F53 -> 427
B54: 8 | C54: 45688 | D54: pago capital ( Carlos Peñafiel) | E54: 100 | G54: =G53+E54-F54 -> 527
B55: 8 | C55: 45688 | D55: pago capital (Lizandro Pruna) | E55: 200 | G55: =G54+E55-F55 -> 727
B56: 8 | C56: 45688 | D56: interes cobrado | E56: 58 | G56: =G55+E56-F56 -> 785 | H56: =+SUM(E52:E56) -> 638
B57: 8 | C57: 45688 | D57: Credito Norma Moscuy | F57: 100 | G57: =G56+E57-F57 -> 685
B58: 8 | C58: 45688 | D58: credito Anthony Moscuy | F58: 100 | G58: =G57+E58-F58 -> 585
B59: 8 | C59: 45688 | D59: credito Marina Chicaiza | F59: 200 | G59: =G58+E59-F59 -> 385
B60: 8 | C60: 45688 | D60: Credito Carmen Herrera | F60: 200 | G60: =G59+E60-F60 -> 185
B61: 8 | C61: 45688 | D61: credito monica moscuy | F61: 100 | G61: =G60+E61-F61 -> 85
B62: 8 | C62: 45688 | D62: credito Rafael molina | F62: 100 | G62: =G61+E62-F62 -> -15
B63: 9 | C63: 45691 | D63: Ingreso ahorro | E63: 125 | G63: =G62+E63-F63 -> 110
B64: 9 | C64: 45691 | D64: pago capital joana herrera | E64: 80 | G64: =G63+E64-F64 -> 190
B65: 9 | C65: 45691 | D65: pago capital norma pruna | E65: 100 | G65: =G64+E65-F65 -> 290
B66: 9 | C66: 45691 | D66: paga capital rocio moscuy | E66: 200 | G66: =G65+E66-F66 -> 490
B67: 9 | C67: 45691 | D67: interes cobrado | E67: 69 | G67: =G66+E67-F67 -> 559 | H67: =+SUM(E64:E67) -> 449
B68: 9 | C68: 45691 | D68: credito Joana Herrera | F68: 100 | G68: =G67+E68-F68 -> 459
B69: 9 | C69: 45691 | D69: credito norma pruna | F69: 100 | G69: =G68+E69-F69 -> 359
B70: 9 | C70: 45691 | D70: Credito Rocio Moscuy | F70: 200 | G70: =G69+E70-F70 -> 159
B71: 9 | C71: 45691 | D71: credito naomi pruna | F71: 100 | G71: =G70+E71-F71 -> 59
B72: 9 | C72: 45691 | D72: credito elsa herrera | F72: 100 | G72: =G71+E72-F72 -> -41
B73: 10 | C73: 45747 | D73: Ingreso ahorro | E73: 125 | G73: =G72+E73-F73 -> 84
B74: 10 | C74: 45747 | D74: pago capital Alex Zapata | E74: 200 | G74: =G73+E74-F74 -> 284
B75: 10 | C75: 45747 | D75: interes cobrado | E75: 80 | G75: =G74+E75-F75 -> 364 | H75: =+SUM(E74:E75) -> 280
B76: 10 | C76: 45747 | D76: Credito Alex Zapata | F76: 200 | G76: =G75+E76-F76 -> 164
B77: 10 | C77: 45747 | D77: credito heliberto Alvarez | F77: 100 | G77: =G76+E77-F77 -> 64
B78: 10 | C78: 45747 | D78: credito Miriam Rodriguez | F78: 100 | G78: =G77+E78-F78 -> -36
B79: 11 | C79: 45777 | D79: Ingreso ahorro | E79: 125 | G79: =G78+E79-F79 -> 89
B80: 11 | C80: 45777 | D80: pago capital marina chicaiza | E80: 200 | G80: =G79+E80-F80 -> 289
B81: 11 | C81: 45777 | D81: pago capital anthony moscuy | E81: 100 | G81: =G80+E81-F81 -> 389
B82: 11 | C82: 45777 | D82: pago capital monica moscuy | E82: 100 | G82: =G81+E82-F82 -> 489
B83: 11 | C83: 45777 | D83: pago capital norma pruna | E83: 100 | G83: =G82+E83-F83 -> 589
B84: 11 | C84: 45777 | D84: pago capital carmen herrera | E84: 200 | G84: =G83+E84-F84 -> 789
B85: 11 | C85: 45777 | D85: pago capital norma moscuy | E85: 100 | G85: =G84+E85-F85 -> 889
B86: 11 | C86: 45777 | D86: pago capital rafael molina | E86: 100 | G86: =G85+E86-F86 -> 989
B87: 11 | C87: 45777 | D87: interes cobrado | E87: 90 | G87: =G86+E87-F87 -> 1079 | H87: =+SUM(E80:E87) -> 990
B88: 11 | C88: 45777 | D88: credito Marina Chicaiza | F88: 100 | G88: =G87+E88-F88 -> 979
B89: 11 | C89: 45777 | D89: Credito Carmen Herrera | F89: 200 | G89: =G88+E89-F89 -> 779
B90: 11 | C90: 45777 | D90: credito norma moscuy | F90: 100 | G90: =G89+E90-F90 -> 679
B91: 11 | C91: 45777 | D91: credito Rafael molina | F91: 100 | G91: =G90+E91-F91 -> 579
B92: 11 | C92: 45777 | D92: credito leydi pruna | F92: 100 | G92: =G91+E92-F92 -> 479
B93: 11 | C93: 45777 | D93: credito mauricio peñafiel | F93: 300 | G93: =G92+E93-F93 -> 179
B94: 11 | C94: 45777 | D94: credito kelly pruna | F94: 100 | G94: =G93+E94-F94 -> 79
B95: 11 | C95: 45777 | D95: credito de victor moscuy | F95: 100 | G95: =G94+E95-F95 -> -21
B96: 11 | C96: 45807 | D96: Ingreso ahorro | E96: 125 | G96: =G95+E96-F96 -> 104
B97: 11 | C97: 45807 | D97: pago capital joana herrera | E97: 100 | G97: =G96+E97-F97 -> 204 | J97: =125+100+100+100+200+100 -> 725
B98: 11 | C98: 45807 | D98: pago capital Naomi Pruna | E98: 100 | G98: =G97+E98-F98 -> 304 | J98: =-21-200-100-200-100-100 -> -721
B99: 11 | C99: 45807 | D99: pago capital Moscuy Rocio | E99: 200 | G99: =G98+E99-F99 -> 504 | J99: =J97+J98 -> 4
B100: 11 | C100: 45807 | D100: pago capital Herrera Elsa | E100: 100 | G100: =G99+E100-F100 -> 604
B101: 11 | C101: 45807 | D101: intèrese cobrados | E101: 100 | G101: =G100+E101-F101 -> 704 | H101: =+SUM(E97:E101) -> 600
B102: 11 | C102: 45807 | D102: crèdito Carlos Peñafiel | F102: 200 | G102: =G101+E102-F102 -> 504
...

Sheet RAPA
B1: CAJA DE AHORRO
B3: COMUNAL
B4: VERDECOCHA
B5: Sembrando juntos para un futuro
D7: NOMBRES | E7: REUNION 1 | P7: REUNION 2 | AA7: REUNION 3 | AK7: REUNION 4 | AU7: REUNION 5 | BE7: REUNION 6 | BO7: REUNION 7 | BY7: REUNION 8 | CI7: REUNION 9 | CS7: REUNION 10 | DC7: REUNION 11 | DM7: 12 | DW7: REUNION | EG7: REUNION | EQ7: REUNION | FA7: REUNION | FK7: REUNION | FW7: REUNION 12 | GG7: REUNION 13 | GQ7: REUNION 14
E8: JUNIO DE 2024 | P8: FECHA: JULIO DE 2024 | AA8: FECHA: AGOSTO DE 2024 | AK8: FECHA: SEPTIEMBRE DE 2024 | AU8: FECHA: OCTUBRE DE 2024 | BE8: FECHA: NOVIEMBRE DE 2024 | BO8: FECHA: DICIEMBRE DE 2024 | BY8: FECHA: ENERO DE 2025 | CI8: FECHA: FEBRERO DEL 2025 | CS8: FECHA: MARZO 2025 | DC8: FECHA: ABRIL (2 MAYO) 2025 | DM8: FECHA: 06 de enero de 2018 | DW8: FECHA: | EG8: FECHA: | EQ8: FECHA: | FA8: FECHA: | FK8: FECHA: | FW8: FECHA: MAYO 2025 | GG8: FECHA: JUNIO 2025 | GQ8: FECHA: JULIO 2025
A9: Nº | E9: SALDO ACTUAL | F9: AHORROS | I9: PRESTAMOS | N9: MULTAS Y OTROS CARGOS | P9: ASISTENCIA | Q9: AHORROS | T9: PRESTAMOS | Y9: APORTES DE SOLIDARIDAD | Z9: MULTAS Y OTROS CARGOS | AA9: ASISTENCIA | AB9: AHORROS | AE9: PRESTAMOS | AJ9: MULTAS Y OTROS CARGOS | AL9: AHORROS | AO9: PRESTAMOS | AT9: MULTAS Y OTROS CARGOS | AU9: ASISTENCIA | AV9: AHORROS | AY9: PRESTAMOS | BD9: MULTAS Y OTROS CARGOS | BE9: ASISTENCIA | BF9: AHORROS | BI9: PRESTAMOS | BN9: MULTAS Y OTROS CARGOS | BO9: ASISTENCIA | BP9: AHORROS | BS9: PRESTAMOS | BX9: MULTAS Y OTROS CARGOS | BY9: ASISTENCIA | BZ9: AHORROS | CC9: PRESTAMOS | CH9: MULTAS Y OTROS CARGOS | CI9: ASISTENCIA | CJ9: AHORROS | CM9: PRESTAMOS | CR9: MULTAS Y OTROS CARGOS | CS9: ASISTENCIA | CT9: AHORROS | CW9: PRESTAMOS | DB9: MULTAS Y OTROS CARGOS | DC9: ASISTENCIA | DD9: AHORROS | DG9: PRESTAMOS | DL9: MULTAS Y OTROS CARGOS | DM9: ASISTENCIA | DN9: AHORROS | DQ9: PRESTAMOS | DV9: MULTAS Y OTROS CARGOS | DW9: ASISTENCIA | DX9: AHORROS | EA9: PRESTAMOS | EF9: MULTAS Y OTROS CARGOS | EG9: ASISTENCIA | EH9: AHORROS | EK9: PRESTAMOS | EP9: MULTAS Y OTROS CARGOS | EQ9: ASISTENCIA | ER9: AHORROS | EU9: PRESTAMOS | EZ9: MULTAS Y OTROS CARGOS | FA9: ASISTENCIA | FB9: AHORROS | FE9: PRESTAMOS | FJ9: MULTAS Y OTROS CARGOS | FK9: ASISTENCIA | FL9: AHORROS | FO9: PRESTAMOS | FT9: MULTAS Y OTROS CARGOS | FW9: ASISTENCIA | FX9: AHORROS | GA9: PRESTAMOS | GF9: MULTAS Y OTROS CARGOS | GG9: ASISTENCIA | GH9: AHORROS | GK9: PRESTAMOS | GP9: MULTAS Y OTROS CARGOS | GQ9: ASISTENCIA | GR9: AHORROS | GU9: PRESTAMOS | GZ9: MULTAS Y OTROS CARGOS
B10: N° SOCIO | C10: N° | F10: APORTE INICIAL | G10: RETIRO | H10: SALDO | I10: CONCEDIDO | J10: INTERES | K10: TOTAL ADEUDADO | L10: PAGO DE PRESTAMO MAS INTERES | M10: SALDO DE PRESTAMO | Q10: AHORRO | R10: RETIRO | S10: SALDO | T10: CONCEDIDO | U10: INTERES | V10: TOTAL ADEUDADO | W10: PAGO DE PRESTAMO MAS INTERES | X10: SALDO DE PRESTAMO | AB10: AHORRO | AC10: RETIRO | AD10: SALDO | AE10: CONCEDIDO | AF10: INTERES | AG10: TOTAL ADEUDADO | AH10: PAGO DE PRESTAMO MAS INTERES | AI10: SALDO DE PRESTAMO | AL10: AHORRO | AM10: RETIRO | AN10: SALDO | AO10: CONCEDIDO | AP10: INTERES | AQ10: TOTAL ADEUDADO | AR10: PAGO DE PRESTAMO MAS INTERES | AS10: SALDO DE PRESTAMO | AV10: AHORRO | AW10: RETIRO | AX10: SALDO | AY10: CONCEDIDO | AZ10: INTERES | BA10: TOTAL ADEUDADO | BB10: PAGO DE PRESTAMO MAS INTERES | BC10: SALDO DE PRESTAMO | BF10: AHORRO | BG10: RETIRO | BH10: SALDO | BI10: CONCEDIDO | BJ10: INTERES | BK10: TOTAL ADEUDADO | BL10: PAGO DE PRESTAMO MAS INTERES | BM10: SALDO DE PRESTAMO | BP10: 1 | BQ10: RETIRO | BR10: SALDO | BS10: CONCEDIDO | BT10: INTERES | BU10: TOTAL ADEUDADO | BV10: PAGO DE PRESTAMO MAS INTERES | BW10: SALDO DE PRESTAMO | BZ10: AHORRO | CA10: RETIRO | CB10: SALDO | CC10: CONCEDIDO | CD10: INTERES | CE10: TOTAL ADEUDADO | CF10: PAGO DE PRESTAMO MAS INTERES | CG10: SALDO DE PRESTAMO | CJ10: AHORRO | CK10: RETIRO | CL10: SALDO | CM10: CONCEDIDO | CN10: INTERES | CO10: TOTAL ADEUDADO | CP10: PAGO DE PRESTAMO MAS INTERES | CQ10: SALDO DE PRESTAMO | CT10: AHORRO | CU10: RETIRO | CV10: SALDO | CW10: CONCEDIDO | CX10: INTERES | CY10: TOTAL ADEUDADO | CZ10: PAGO DE PRESTAMO MAS INTERES | DA10: SALDO DE PRESTAMO | DD10: AHORRO | DE10: RETIRO | DF10: SALDO | DG10: CONCEDIDO | DH10: INTERES | DI10: TOTAL ADEUDADO | DJ10: PAGO DE PRESTAMO MAS INTERES | DK10: SALDO DE PRESTAMO | DN10: AHORRO | DO10: RETIRO | DP10: SALDO | DQ10: CONCEDIDO | DR10: INTERES | DS10: TOTAL ADEUDADO | DT10: PAGO DE PRESTAMO MAS INTERES | DU10: SALDO DE PRESTAMO | DX10: AHORRO | DY10: RETIRO | DZ10: SALDO | EA10: CONCEDIDO | EB10: INTERES | EC10: TOTAL ADEUDADO | ED10: PAGO DE PRESTAMO MAS INTERES | EE10: SALDO DE PRESTAMO | EH10: AHORRO | EI10: RETIRO | EJ10: SALDO | EK10: CONCEDIDO | EL10: INTERES | EM10: TOTAL ADEUDADO | EN10: PAGO DE PRESTAMO MAS INTERES | EO10: SALDO DE PRESTAMO | ER10: AHORRO | ES10: RETIRO | ET10: SALDO | EU10: CONCEDIDO | EV10: INTERES | EW10: TOTAL ADEUDADO | EX10: PAGO DE PRESTAMO MAS INTERES | EY10: SALDO DE PRESTAMO | FB10: AHORRO | FC10: RETIRO | FD10: SALDO | FE10: CONCEDIDO | FF10: INTERES | FG10: TOTAL ADEUDADO | FH10: PAGO DE PRESTAMO MAS INTERES | FI10: SALDO DE PRESTAMO | FL10: AHORRO | FM10: RETIRO | FN10: SALDO | FO10: CONCEDIDO | FP10: INTERES | FQ10: TOTAL ADEUDADO | FR10: PAGO DE PRESTAMO MAS INTERES | FS10: SALDO DE PRESTAMO | FX10: AHORRO | FY10: RETIRO | FZ10: SALDO | GA10: CONCEDIDO | GB10: INTERES | GC10: TOTAL ADEUDADO | GD10: PAGO DE PRESTAMO MAS INTERES | GE10: SALDO DE PRESTAMO | GH10: AHORRO | GI10: RETIRO | GJ10: SALDO | GK10: CONCEDIDO | GL10: INTERES | GM10: TOTAL ADEUDADO | GN10: PAGO DE PRESTAMO MAS INTERES | GO10: SALDO DE PRESTAMO | GR10: AHORRO | GS10: RETIRO | GT10: SALDO | GU10: CONCEDIDO | GV10: INTERES | GW10: TOTAL ADEUDADO | GX10: PAGO DE PRESTAMO MAS INTERES | GY10: SALDO DE PRESTAMO
A11: 1 | B11: 1 | C11: 1 | D11: ALVAREZ PRUNA LUIS HERIBERTO | E11: 0 | F11: 10 | H11: =E11+F11-G11 -> 10 | M11: =+I11+J11-L11 -> 0 | Q11: 5 | S11: =H11+Q11-R11 -> 15 | V11: =T11+U11 -> 0 | X11: =M11+T11+U11-W11 -> 0 | AB11: 5 | AD11: =S11+AB11-AC11 -> 20 | AG11: =AE11+AF11 -> 0 | AI11: =X11+AE11+AF11-AH11 -> 0 | AL11: 5 | AN11: =AD11+AL11-AM11 -> 25 | AQ11: =AO11+AP11 -> 0 | AS11: =AI11+AO11+AP11-AR11 -> 0 | AV11: 5 | AX11: =AN11+AV11-AW11 -> 30 | BA11: =AY11+AZ11 -> 0 | BC11: =AS11+AY11+AZ11-BB11 -> 0 | BF11: 5 | BH11: =AX11+BF11-BG11 -> 35 | BK11: =BI11+BJ11 -> 0 | BM11: =BC11+BI11+BJ11-BL11 -> 0 | BP11: 5 | BR11: =BH11+BP11-BQ11 -> 40 | BU11: =BS11+BT11 -> 0 | BW11: =BM11+BS11+BT11-BV11 -> 0 | BZ11: 5 | CB11: =BR11+BZ11-CA11 -> 45 | CE11: =CC11+CD11 -> 0 | CG11: =BW11+CC11+CD11-CF11 -> 0 | CJ11: 5 | CL11: =CB11+CJ11-CK11 -> 50 | CO11: =CM11+CN11 -> 0 | CQ11: =CG11+CM11+CN11-CP11 -> 0 | CT11: 5 | CV11: =CL11+CT11-CU11 -> 55 | CW11: 100 | CX11: 15 | CY11: =CW11+CX11 -> 115 | DA11: =CQ11+CW11+CX11-CZ11 -> 115 | DD11: 5 | DF11: =CV11+DD11-DE11 -> 60 | DI11: =DG11+DH11 -> 0 | DJ11: 5 | DK11: =DA11+DG11+DH11-DJ11 -> 110 | DN11: 11.77 | DP11: =DF11+DN11-DO11 -> 71.77 | DS11: =DQ11+DR11 -> 0 | DT11: 13.23 | DU11: =DK11+DQ11+DR11-DT11 -> 96.77 | DZ11: =DP11+DX11-DY11 -> 71.77 | EC11: =EA11+EB11 -> 0 | EE11: =DU11+EA11+EB11-ED11 -> 96.77 | EJ11: =DZ11+EH11-EI11 -> 71.77 | EM11: =EK11+EL11 -> 0 | EO11: =EE11+EK11+EL11-EN11 -> 96.77 | ET11: =EJ11+ER11-ES11 -> 71.77 | EW11: =EU11+EV11 -> 0 | EY11: =EO11+EU11+EV11-EX11 -> 96.77 | FD11: =ET11+FB11-FC11 -> 71.77 | FG11: =FE11+FF11 -> 0 | FI11: =EY11+FE11+FF11-FH11 -> 96.77 | FN11: =FD11+FL11-FM11 -> 71.77 | FQ11: =FO11+FP11 -> 0 | FS11: =FI11+FO11+FP11-FR11 -> 96.77 | FX11: 5 | FZ11: =DF11+FX11-FY11 -> 65 | GC11: =GA11+GB11 -> 0 | GD11: 5 | GE11: =DK11+GC11-GD11 -> 105 | GH11: 5 | GJ11: =+FZ11+GH11-GI11 -> 70 | GM11: =GK11+GL11 -> 0 | GN11: 105 | GO11: =+GE11+GM11-GN11 -> 0 | GT11: =GJ11+GR11-GS11 -> 70 | GW11: =GU11+GV11 -> 0 | GY11: =+GO11+GW11-GX11 -> 0
A12: 2 | B12: 2 | C12: 2 | D12: CHACHAPOYA TOAPANTA RAUL GERARDO | E12: 0 | F12: 10 | H12: =E12+F12-G12 -> 10 | M12: =+I12+J12-L12 -> 0 | Q12: 5 | S12: =H12+Q12-R12 -> 15 | V12: =T12+U12 -> 0 | X12: =M12+T12+U12-W12 -> 0 | AB12: 5 | AD12: =S12+AB12-AC12 -> 20 | AG12: =AE12+AF12 -> 0 | AI12: =X12+AE12+AF12-AH12 -> 0 | AL12: 5 | AN12: =AD12+AL12-AM12 -> 25 | AQ12: =AO12+AP12 -> 0 | AS12: =AI12+AO12+AP12-AR12 -> 0 | AV12: 5 | AX12: =AN12+AV12-AW12 -> 30 | BA12: =AY12+AZ12 -> 0 | BC12: =AS12+AY12+AZ12-BB12 -> 0 | BF12: 5 | BH12: =AX12+BF12-BG12 -> 35 | BK12: =BI12+BJ12 -> 0 | BM12: =BC12+BI12+BJ12-BL12 -> 0 | BP12: 5 | BR12: =BH12+BP12-BQ12 -> 40 | BU12: =BS12+BT12 -> 0 | BW12: =BM12+BS12+BT12-BV12 -> 0 | BZ12: 5 | CB12: =BR12+BZ12-CA12 -> 45 | CE12: =CC12+CD12 -> 0 | CG12: =BW12+CC12+CD12-CF12 -> 0 | CJ12: 5 | CL12: =CB12+CJ12-CK12 -> 50 | CO12: =CM12+CN12 -> 0 | CQ12: =CG12+CM12+CN12-CP12 -> 0 | CT12: 5 | CV12: =CL12+CT12-CU12 -> 55 | CY12: =CW12+CX12 -> 0 | DA12: =CQ12+CW12+CX12-CZ12 -> 0 | DD12: 5 | DF12: =CV12+DD12-DE12 -> 60 | DI12: =DG12+DH12 -> 0 | DK12: =DA12+DG12+DH12-DJ12 -> 0 | DN12: 11.45 | DP12: =DF12+DN12-DO12 -> 71.45 | DS12: =DQ12+DR12 -> 0 | DT12: 88.55 | DU12: =DK12+DQ12+DR12-DT12 -> -88.55 | DZ12: =DP12+DX12-DY12 -> 71.45 | EC12: =EA12+EB12 -> 0 | EE12: =DU12+EA12+EB12-ED12 -> -88.55 | EJ12: =DZ12+EH12-EI12 -> 71.45 | EM12: =EK12+EL12 -> 0 | EO12: =EE12+EK12+EL12-EN12 -> -88.55 | ET12: =EJ12+ER12-ES12 -> 71.45 | EW12: =EU12+EV12 -> 0 | EY12: =EO12+EU12+EV12-EX12 -> -88.55 | FD12: =ET12+FB12-FC12 -> 71.45 | FG12: =FE12+FF12 -> 0 | FI12: =EY12+FE12+FF12-FH12 -> -88.55 | FN12: =FD12+FL12-FM12 -> 71.45 | FQ12: =FO12+FP12 -> 0 | FS12: =FI12+FO12+FP12-FR12 -> -88.55 | FX12: 5 | FZ12: =DF12+FX12-FY12 -> 65 | GC12: =GA12+GB12 -> 0 | GE12: =DK12+GC12-GD12 -> 0 | GH12: 5 | GJ12: =+FZ12+GH12-GI12 -> 70 | GK12: 100 | GL12: 15 | GM12: =GK12+GL12 -> 115 | GO12: =+GE12+GM12-GN12 -> 115 | GT12: =GJ12+GR12-GS12 -> 70 | GW12: =GU12+GV12 -> 0 | GY12: =+GO12+GW12-GX12 -> 115
A13: 3 | B13: 3 | C13: 3 | D13: CHICAIZA CHACON GLORIA MARINA | E13: 0 | F13: 10 | H13: =E13+F13-G13 -> 10 | M13: =+I13+J13-L13 -> 0 | Q13: 5 | S13: =H13+Q13-R13 -> 15 | V13: =T13+U13 -> 0 | X13: =M13+T13+U13-W13 -> 0 | AB13: 5 | AD13: =S13+AB13-AC13 -> 20 | AG13: =AE13+AF13 -> 0 | AI13: =X13+AE13+AF13-AH13 -> 0 | AL13: 5 | AN13: =AD13+AL13-AM13 -> 25 | AQ13: =AO13+AP13 -> 0 | AS13: =AI13+AO13+AP13-AR13 -> 0 | AV13: 5 | AX13: =AN13+AV13-AW13 -> 30 | BA13: =AY13+AZ13 -> 0 | BC13: =AS13+AY13+AZ13-BB13 -> 0 | BF13: 5 | BH13: =AX13+BF13-BG13 -> 35 | BK13: =BI13+BJ13 -> 0 | BM13: =BC13+BI13+BJ13-BL13 -> 0 | BP13: 5 | BR13: =BH13+BP13-BQ13 -> 40 | BU13: =BS13+BT13 -> 0 | BW13: =BM13+BS13+BT13-BV13 -> 0 | BZ13: 5 | CB13: =BR13+BZ13-CA13 -> 45 | CC13: 200 | CD13: 30 | CE13: =CC13+CD13 -> 230 | CG13: =BW13+CC13+CD13-CF13 -> 230 | CJ13: 5 | CL13: =CB13+CJ13-CK13 -> 50 | CO13: =CM13+CN13 -> 0 | CP13: 10 | CQ13: =CG13+CM13+CN13-CP13 -> 220 | CT13: 5 | CV13: =CL13+CT13-CU13 -> 55 | CY13: =CW13+CX13 -> 0 | CZ13: 10 | DA13: =CQ13+CW13+CX13-CZ13 -> 210 | DD13: 5 | DF13: =CV13+DD13-DE13 -> 60 | DG13: 100 | DH13: 15 | DI13: =DG13+DH13 -> 115 | DJ13: 210 | DK13: =DA13+DG13+DH13-DJ13 -> 115 | DN13: 10 | DP13: =DF13+DN13-DO13 -> 70 | DS13: =DQ13+DR13 -> 0 | DU13: =DK13+DQ13+DR13-DT13 -> 115 | DZ13: =DP13+DX13-DY13 -> 70 | EC13: =EA13+EB13 -> 0 | EE13: =DU13+EA13+EB13-ED13 -> 115 | EJ13: =DZ13+EH13-EI13 -> 70 | EM13: =EK13+EL13 -> 0 | EO13: =EE13+EK13+EL13-EN13 -> 115 | ET13: =EJ13+ER13-ES13 -> 70 | EW13: =EU13+EV13 -> 0 | EY13: =EO13+EU13+EV13-EX13 -> 115 | FD13: =ET13+FB13-FC13 -> 70 | FG13: =FE13+FF13 -> 0 | FI13: =EY13+FE13+FF13-FH13 -> 115 | FN13: =FD13+FL13-FM13 -> 70 | FQ13: =FO13+FP13 -> 0 | FS13: =FI13+FO13+FP13-FR13 -> 115 | FX13: 5 | FZ13: =DF13+FX13-FY13 -> 65 | GC13: =GA13+GB13 -> 0 | GD13: 5 | GE13: =DK13+GC13-GD13 -> 110 | GH13: 5 | GJ13: =+FZ13+GH13-GI13 -> 70 | GM13: =GK13+GL13 -> 0 | GO13: =+GE13+GM13-GN13 -> 110 | GT13: =GJ13+GR13-GS13 -> 70 | GW13: =GU13+GV13 -> 0 | GY13: =+GO13+GW13-GX13 -> 110
A14: 4 | B14: 4 | C14: 4 | D14: HERRERA ZAPATA CARMEN ALICIA | E14: 0 | F14: 10 | H14: =E14+F14-G14 -> 10 | M14: =+I14+J14-L14 -> 0 | Q14: 5 | S14: =H14+Q14-R14 -> 15 | T14: 100 | U14: 15 | V14: =T14+U14 -> 115 | X14: =M14+T14+U14-W14 -> 115 | AB14: 5 | AD14: =S14+AB14-AC14 -> 20 | AG14: =AE14+AF14 -> 0 | AH14: 5 | AI14: =X14+AE14+AF14-AH14 -> 110 | AL14: 5 | AN14: =AD14+AL14-AM14 -> 25 | AQ14: =AO14+AP14 -> 0 | AR14: 5 | AS14: =AI14+AO14+AP14-AR14 -> 105 | AV14: 5 | AX14: =AN14+AV14-AW14 -> 30 | AY14: 180 | AZ14: 27 | BA14: =AY14+AZ14 -> 207 | BB14: 105 | BC14: =AS14+AY14+AZ14-BB14 -> 207 | BF14: 5 | BH14: =AX14+BF14-BG14 -> 35 | BK14: =BI14+BJ14 -> 0 | BL14: 9 | BM14: =BC14+BI14+BJ14-BL14 -> 198 | BP14: 5 | BR14: =BH14+BP14-BQ14 -> 40 | BU14: =BS14+BT14 -> 0 | BV14: 9 | BW14: =BM14+BS14+BT14-BV14 -> 189 | BZ14: 5 | CB14: =BR14+BZ14-CA14 -> 45 | CC14: 200 | CD14: 30 | CE14: =CC14+CD14 -> 230 | CF14: 189 | CG14: =BW14+CC14+CD14-CF14 -> 230 | CJ14: 5 | CL14: =CB14+CJ14-CK14 -> 50 | CO14: =CM14+CN14 -> 0 | CP14: 10 | CQ14: =CG14+CM14+CN14-CP14 -> 220 | CT14: 5 | CV14: =CL14+CT14-CU14 -> 55 | CY14: =CW14+CX14 -> 0 | CZ14: 10 | DA14: =CQ14+CW14+CX14-CZ14 -> 210 | DD14: 5 | DF14: =CV14+DD14-DE14 -> 60 | DG14: 200 | DH14: 30 | DI14: =DG14+DH14 -> 230 | DJ14: 210 | DK14: =DA14+DG14+DH14-DJ14 -> 230 | DN14: 13.33 | DP14: =DF14+DN14-DO14 -> 73.33 | DS14: =DQ14+DR14 -> 0 | DT14: 56.67 | DU14: =DK14+DQ14+DR14-DT14 -> 173.33 | DZ14: =DP14+DX14-DY14 -> 73.33 | EC14: =EA14+EB14 -> 0 | EE14: =DU14+EA14+EB14-ED14 -> 173.33 | EJ14: =DZ14+EH14-EI14 -> 73.33 | EM14: =EK14+EL14 -> 0 | EO14: =EE14+EK14+EL14-EN14 -> 173.33 | ET14: =EJ14+ER14-ES14 -> 73.33 | EW14: =EU14+EV14 -> 0 | EY14: =EO14+EU14+EV14-EX14 -> 173.33 | FD14: =ET14+FB14-FC14 -> 73.33 | FG14: =FE14+FF14 -> 0 | FI14: =EY14+FE14+FF14-FH14 -> 173.33 | FN14: =FD14+FL14-FM14 -> 73.33 | FQ14: =FO14+FP14 -> 0 | FS14: =FI14+FO14+FP14-FR14 -> 173.33 | FX14: 5 | FZ14: =DF14+FX14-FY14 -> 65 | GC14: =GA14+GB14 -> 0 | GD14: 10 | GE14: =DK14+GC14-GD14 -> 220 | GH14: 5 | GJ14: =+FZ14+GH14-GI14 -> 70 | GK14: 135 | GL14: 20.25 | GM14: =GK14+GL14 -> 155.25 | GO14: =+GE14+GM14-GN14 -> 375.25 | GT14: =GJ14+GR14-GS14 -> 70 | GW14: =GU14+GV14 -> 0 | GY14: =+GO14+GW14-GX14 -> 375.25
A15: 5 | B15: 5 | C15: 5 | D15: HERRERA ZAPATA ELSA PIEDAD | E15: 0 | F15: 10 | H15: =E15+F15-G15 -> 10 | M15: =+I15+J15-L15 -> 0 | Q15: 5 | S15: =H15+Q15-R15 -> 15 | V15: =T15+U15 -> 0 | X15: =M15+T15+U15-W15 -> 0 | AB15: 5 | AD15: =S15+AB15-AC15 -> 20 | AG15: =AE15+AF15 -> 0 | AI15: =X15+AE15+AF15-AH15 -> 0 | AL15: 5 | AN15: =AD15+AL15-AM15 -> 25 | AQ15: =AO15+AP15 -> 0 | AS15: =AI15+AO15+AP15-AR15 -> 0 | AV15: 5 | AX15: =AN15+AV15-AW15 -> 30 | BA15: =AY15+AZ15 -> 0 | BC15: =AS15+AY15+AZ15-BB15 -> 0 | BF15: 5 | BH15: =AX15+BF15-BG15 -> 35 | BK15: =BI15+BJ15 -> 0 | BM15: =BC15+BI15+BJ15-BL15 -> 0 | BP15: 5 | BR15: =BH15+BP15-BQ15 -> 40 | BU15: =BS15+BT15 -> 0 | BW15: =BM15+BS15+BT15-BV15 -> 0 | BZ15: 5 | CB15: =BR15+BZ15-CA15 -> 45 | CE15: =CC15+CD15 -> 0 | CG15: =BW15+CC15+CD15-CF15 -> 0 | CJ15: 5 | CL15: =CB15+CJ15-CK15 -> 50 | CM15: 100 | CN15: 15 | CO15: =CM15+CN15 -> 115 | CQ15: =CG15+CM15+CN15-CP15 -> 115 | CT15: 5 | CV15: =CL15+CT15-CU15 -> 55 | CY15: =CW15+CX15 -> 0 | CZ15: 5 | DA15: =CQ15+CW15+CX15-CZ15 -> 110 | DD15: 5 | DF15: =CV15+DD15-DE15 -> 60 | DI15: =DG15+DH15 -> 0 | DJ15: 5 | DK15: =DA15+DG15+DH15-DJ15 -> 105 | DN15: 13.79 | DP15: =DF15+DN15-DO15 -> 73.79 | DS15: =DQ15+DR15 -> 0 | DT15: 176.21 | DU15: =DK15+DQ15+DR15-DT15 -> -71.21 | DZ15: =DP15+DX15-DY15 -> 73.79 | EC15: =EA15+EB15 -> 0 | EE15: =DU15+EA15+EB15-ED15 -> -71.21 | EJ15: =DZ15+EH15-EI15 -> 73.79 | EM15: =EK15+EL15 -> 0 | EO15: =EE15+EK15+EL15-EN15 -> -71.21 | ET15: =EJ15+ER15-ES15 -> 73.79 | EW15: =EU15+EV15 -> 0 | EY15: =EO15+EU15+EV15-EX15 -> -71.21 | FD15: =ET15+FB15-FC15 -> 73.79 | FG15: =FE15+FF15 -> 0 | FI15: =EY15+FE15+FF15-FH15 -> -71.21 | FN15: =FD15+FL15-FM15 -> 73.79 | FQ15: =FO15+FP15 -> 0 | FS15: =FI15+FO15+FP15-FR15 -> -71.21 | FX15: 5 | FZ15: =DF15+FX15-FY15 -> 65 | GA15: 100 | GB15: 15 | GC15: =GA15+GB15 -> 115 | GD15: 105 | GE15: =DK15+GC15-GD15 -> 115 | GH15: 5 | GJ15: =+FZ15+GH15-GI15 -> 70 | GM15: =GK15+GL15 -> 0 | GO15: =+GE15+GM15-GN15 -> 115 | GT15: =GJ15+GR15-GS15 -> 70 | GW15: =GU15+GV15 -> 0 | GY15: =+GO15+GW15-GX15 -> 115
A16: 6 | B16: 6 | C16: 6 | D16: HERRERA HERRERA JOANA ALEXANDRA | E16: 0 | F16: 10 | H16: =E16+F16-G16 -> 10 | M16: =+I16+J16-L16 -> 0 | Q16: 5 | S16: =H16+Q16-R16 -> 15 | V16: =T16+U16 -> 0 | X16: =M16+T16+U16-W16 -> 0 | AB16: 5 | AD16: =S16+AB16-AC16 -> 20 | AG16: =AE16+AF16 -> 0 | AI16: =X16+AE16+AF16-AH16 -> 0 | AL16: 5 | AN16: =AD16+AL16-AM16 -> 25 | AO16: 100 | AP16: 15 | AQ16: =AO16+AP16 -> 115 | AS16: =AI16+AO16+AP16-AR16 -> 115 | AV16: 5 | AX16: =AN16+AV16-AW16 -> 30 | BA16: =AY16+AZ16 -> 0 | BB16: 5 | BC16: =AS16+AY16+AZ16-BB16 -> 110 | BF16: 5 | BH16: =AX16+BF16-BG16 -> 35 | BI16: 80 | BJ16: 12 | BK16: =BI16+BJ16 -> 92 | BL16: 5 | BM16: =BC16+BI16+BJ16-BL16 -> 197 | BP16: 5 | BR16: =BH16+BP16-BQ16 -> 40 | BU16: =BS16+BT16 -> 0 | BV16: 109 | BW16: =BM16+BS16+BT16-BV16 -> 88 | BZ16: 5 | CB16: =BR16+BZ16-CA16 -> 45 | CE16: =CC16+CD16 -> 0 | CF16: 4 | CG16: =BW16+CC16+CD16-CF16 -> 84 | CJ16: 5 | CL16: =CB16+CJ16-CK16 -> 50 | CM16: 100 | CN16: 15 | CO16: =CM16+CN16 -> 115 | CP16: 84 | CQ16: =CG16+CM16+CN16-CP16 -> 115 | CT16: 5 | CV16: =CL16+CT16-CU16 -> 55 | CY16: =CW16+CX16 -> 0 | CZ16: 5 | DA16: =CQ16+CW16+CX16-CZ16 -> 110 | DD16: 5 | DF16: =CV16+DD16-DE16 -> 60 | DI16: =DG16+DH16 -> 0 | DJ16: 5 | DK16: =DA16+DG16+DH16-DJ16 -> 105 | DN16: 10 | DP16: =DF16+DN16-DO16 -> 70 | DS16: =DQ16+DR16 -> 0 | DU16: =DK16+DQ16+DR16-DT16 -> 105 | DZ16: =DP16+DX16-DY16 -> 70 | EC16: =EA16+EB16 -> 0 | EE16: =DU16+EA16+EB16-ED16 -> 105 | EJ16: =DZ16+EH16-EI16 -> 70 | EM16: =EK16+EL16 -> 0 | EO16: =EE16+EK16+EL16-EN16 -> 105 | ET16: =EJ16+ER16-ES16 -> 70 | EW16: =EU16+EV16 -> 0 | EY16: =EO16+EU16+EV16-EX16 -> 105 | FD16: =ET16+FB16-FC16 -> 70 | FG16: =FE16+FF16 -> 0 | FI16: =EY16+FE16+FF16-FH16 -> 105 | FN16: =FD16+FL16-FM16 -> 70 | FQ16: =FO16+FP16 -> 0 | FS16: =FI16+FO16+FP16-FR16 -> 105 | FX16: 5 | FZ16: =DF16+FX16-FY16 -> 65 | GC16: =GA16+GB16 -> 0 | GD16: 105 | GE16: =DK16+GC16-GD16 -> 0 | GH16: 5 | GJ16: =+FZ16+GH16-GI16 -> 70 | GM16: =GK16+GL16 -> 0 | GO16: =+GE16+GM16-GN16 -> 0 | GT16: =GJ16+GR16-GS16 -> 70 | GW16: =GU16+GV16 -> 0 | GY16: =+GO16+GW16-GX16 -> 0
A17: 7 | B17: 7 | C17: 7 | D17: MOLINA BELTRAN LUIS RAFAEL | E17: 0 | F17: 10 | H17: =E17+F17-G17 -> 10 | M17: =+I17+J17-L17 -> 0 | S17: =H17+Q17-R17 -> 10 | V17: =T17+U17 -> 0 | X17: =M17+T17+U17-W17 -> 0 | AD17: =S17+AB17-AC17 -> 10 | AG17: =AE17+AF17 -> 0 | AI17: =X17+AE17+AF17-AH17 -> 0 | AL17: 15 | AN17: =AD17+AL17-AM17 -> 25 | AQ17: =AO17+AP17 -> 0 | AS17: =AI17+AO17+AP17-AR17 -> 0 | AV17: 5 | AX17: =AN17+AV17-AW17 -> 30 | BA17: =AY17+AZ17 -> 0 | BC17: =AS17+AY17+AZ17-BB17 -> 0 | BF17: 5 | BH17: =AX17+BF17-BG17 -> 35 | BK17: =BI17+BJ17 -> 0 | BM17: =BC17+BI17+BJ17-BL17 -> 0 | BP17: 5 | BR17: =BH17+BP17-BQ17 -> 40 | BU17: =BS17+BT17 -> 0 | BW17: =BM17+BS17+BT17-BV17 -> 0 | BZ17: 5 | CB17: =BR17+BZ17-CA17 -> 45 | CC17: 100 | CD17: 15 | CE17: =CC17+CD17 -> 115 | CG17: =BW17+CC17+CD17-CF17 -> 115 | CJ17: 5 | CL17: =CB17+CJ17-CK17 -> 50 | CO17: =CM17+CN17 -> 0 | CP17: 5 | CQ17: =CG17+CM17+CN17-CP17 -> 110 | CT17: 5 | CV17: =CL17+CT17-CU17 -> 55 | CY17: =CW17+CX17 -> 0 | CZ17: 5 | DA17: =CQ17+CW17+CX17-CZ17 -> 105 | DD17: 5 | DF17: =CV17+DD17-DE17 -> 60 | DG17: 100 | DH17: 15 | DI17: =DG17+DH17 -> 115 | DJ17: 105 | DK17: =DA17+DG17+DH17-DJ17 -> 115 | DN17: 10 | DP17: =DF17+DN17-DO17 -> 70 | DS17: =DQ17+DR17 -> 0 | DT17: 88.5 | DU17: =DK17+DQ17+DR17-DT17 -> 26.5 | DZ17: =DP17+DX17-DY17 -> 70 | EC17: =EA17+EB17 -> 0 | EE17: =DU17+EA17+EB17-ED17 -> 26.5 | EJ17: =DZ17+EH17-EI17 -> 70 | EM17: =EK17+EL17 -> 0 | EO17: =EE17+EK17+EL17-EN17 -> 26.5 | ET17: =EJ17+ER17-ES17 -> 70 | EW17: =EU17+EV17 -> 0 | EY17: =EO17+EU17+EV17-EX17 -> 26.5 | FD17: =ET17+FB17-FC17 -> 70 | FG17: =FE17+FF17 -> 0 | FI17: =EY17+FE17+FF17-FH17 -> 26.5 | FN17: =FD17+FL17-FM17 -> 70 | FQ17: =FO17+FP17 -> 0 | FS17: =FI17+FO17+FP17-FR17 -> 26.5 | FX17: 5 | FZ17: =DF17+FX17-FY17 -> 65 | GC17: =GA17+GB17 -> 0 | GD17: 5 | GE17: =DK17+GC17-GD17 -> 110 | GH17: 5 | GJ17: =+FZ17+GH17-GI17 -> 70 | GM17: =GK17+GL17 -> 0 | GO17: =+GE17+GM17-GN17 -> 110 | GT17: =GJ17+GR17-GS17 -> 70 | GW17: =GU17+GV17 -> 0 | GY17: =+GO17+GW17-GX17 -> 110
A18: 8 | B18: 8 | C18: 8 | D18: MONGE PRUNA JOSUE DAMIÁN | E18: 0 | F18: 10 | H18: =E18+F18-G18 -> 10 | M18: =+I18+J18-L18 -> 0 | Q18: 5 | S18: =H18+Q18-R18 -> 15 | V18: =T18+U18 -> 0 | X18: =M18+T18+U18-W18 -> 0 | AB18: 5 | AD18: =S18+AB18-AC18 -> 20 | AG18: =AE18+AF18 -> 0 | AI18: =X18+AE18+AF18-AH18 -> 0 | AL18: 5 | AN18: =AD18+AL18-AM18 -> 25 | AQ18: =AO18+AP18 -> 0 | AS18: =AI18+AO18+AP18-AR18 -> 0 | AV18: 5 | AX18: =AN18+AV18-AW18 -> 30 | BA18: =AY18+AZ18 -> 0 | BC18: =AS18+AY18+AZ18-BB18 -> 0 | BF18: 5 | BH18: =AX18+BF18-BG18 -> 35 | BK18: =BI18+BJ18 -> 0 | BM18: =BC18+BI18+BJ18-BL18 -> 0 | BP18: 5 | BR18: =BH18+BP18-BQ18 -> 40 | BU18: =BS18+BT18 -> 0 | BW18: =BM18+BS18+BT18-BV18 -> 0 | BZ18: 5 | CB18: =BR18+BZ18-CA18 -> 45 | CE18: =CC18+CD18 -> 0 | CG18: =BW18+CC18+CD18-CF18 -> 0 | CJ18: 5 | CL18: =CB18+CJ18-CK18 -> 50 | CO18: =CM18+CN18 -> 0 | CQ18: =CG18+CM18+CN18-CP18 -> 0 | CT18: 5 | CV18: =CL18+CT18-CU18 -> 55 | CY18: =CW18+CX18 -> 0 | DA18: =CQ18+CW18+CX18-CZ18 -> 0 | DD18: 5 | DF18: =CV18+DD18-DE18 -> 60 | DI18: =DG18+DH18 -> 0 | DK18: =DA18+DG18+DH18-DJ18 -> 0 | DN18: 11.7 | DP18: =DF18+DN18-DO18 -> 71.7 | DS18: =DQ18+DR18 -> 0 | DT18: 48.3 | DU18: =DK18+DQ18+DR18-DT18 -> -48.3 | DZ18: =DP18+DX18-DY18 -> 71.7 | EC18: =EA18+EB18 -> 0 | EE18: =DU18+EA18+EB18-ED18 -> -48.3 | EJ18: =DZ18+EH18-EI18 -> 71.7 | EM18: =EK18+EL18 -> 0 | EO18: =EE18+EK18+EL18-EN18 -> -48.3 | ET18: =EJ18+ER18-ES18 -> 71.7 | EW18: =EU18+EV18 -> 0 | EY18: =EO18+EU18+EV18-EX18 -> -48.3 | FD18: =ET18+FB18-FC18 -> 71.7 | FG18: =FE18+FF18 -> 0 | FI18: =EY18+FE18+FF18-FH18 -> -48.3 | FN18: =FD18+FL18-FM18 -> 71.7 | FQ18: =FO18+FP18 -> 0 | FS18: =FI18+FO18+FP18-FR18 -> -48.3 | FX18: 5 | FZ18: =DF18+FX18-FY18 -> 65 | GA18: 100 | GB18: 15 | GC18: =GA18+GB18 -> 115 | GE18: =DK18+GC18-GD18 -> 115 | GH18: 5 | GJ18: =+FZ18+GH18-GI18 -> 70 | GM18: =GK18+GL18 -> 0 | GO18: =+GE18+GM18-GN18 -> 115 | GT18: =GJ18+GR18-GS18 -> 70 | GW18: =GU18+GV18 -> 0 | GY18: =+GO18+GW18-GX18 -> 115
A19: 9 | B19: 9 | C19: 9 | D19: MOSCUY ALVAREZ ANTONY ALEXANDER | F19: 10 | H19: =E19+F19-G19 -> 10 | M19: =+I19+J19-L19 -> 0 | S19: =H19+Q19-R19 -> 10 | V19: =T19+U19 -> 0 | X19: =M19+T19+U19-W19 -> 0 | AB19: 10 | AD19: =S19+AB19-AC19 -> 20 | AG19: =AE19+AF19 -> 0 | AI19: =X19+AE19+AF19-AH19 -> 0 | AL19: 5 | AN19: =AD19+AL19-AM19 -> 25 | AQ19: =AO19+AP19 -> 0 | AS19: =AI19+AO19+AP19-AR19 -> 0 | AV19: 5 | AX19: =AN19+AV19-AW19 -> 30 | AY19: 100 | AZ19: 15 | BA19: =AY19+AZ19 -> 115 | BC19: =AS19+AY19+AZ19-BB19 -> 115 | BF19: 5 | BH19: =AX19+BF19-BG19 -> 35 | BK19: =BI19+BJ19 -> 0 | BL19: 5 | BM19: =BC19+BI19+BJ19-BL19 -> 110 | BP19: 5 | BR19: =BH19+BP19-BQ19 -> 40 | BU19: =BS19+BT19 -> 0 | BV19: 5 | BW19: =BM19+BS19+BT19-BV19 -> 105 | BZ19: 5 | CB19: =BR19+BZ19-CA19 -> 45 | CC19: 100 | CD19: 15 | CE19: =CC19+CD19 -> 115 | CF19: 105 | CG19: =BW19+CC19+CD19-CF19 -> 115 | CJ19: 5 | CL19: =CB19+CJ19-CK19 -> 50 | CO19: =CM19+CN19 -> 0 | CP19: 5 | CQ19: =CG19+CM19+CN19-CP19 -> 110 | CT19: 5 | CV19: =CL19+CT19-CU19 -> 55 | CY19: =CW19+CX19 -> 0 | CZ19: 5 | DA19: =CQ19+CW19+CX19-CZ19 -> 105 | DD19: 5 | DF19: =CV19+DD19-DE19 -> 60 | DI19: =DG19+DH19 -> 0 | DJ19: 105 | DK19: =DA19+DG19+DH19-DJ19 -> 0 | DN19: 13.5 | DP19: =DF19+DN19-DO19 -> 73.5 | DS19: =DQ19+DR19 -> 0 | DT19: 11.5 | DU19: =DK19+DQ19+DR19-DT19 -> -11.5 | DZ19: =DP19+DX19-DY19 -> 73.5 | EC19: =EA19+EB19 -> 0 | EE19: =DU19+EA19+EB19-ED19 -> -11.5 | EJ19: =DZ19+EH19-EI19 -> 73.5 | EM19: =EK19+EL19 -> 0 | EO19: =EE19+EK19+EL19-EN19 -> -11.5 | ET19: =EJ19+ER19-ES19 -> 73.5 | EW19: =EU19+EV19 -> 0 | EY19: =EO19+EU19+EV19-EX19 -> -11.5 | FD19: =ET19+FB19-FC19 -> 73.5 | FG19: =FE19+FF19 -> 0 | FI19: =EY19+FE19+FF19-FH19 -> -11.5 | FN19: =FD19+FL19-FM19 -> 73.5 | FQ19: =FO19+FP19 -> 0 | FS19: =FI19+FO19+FP19-FR19 -> -11.5 | FX19: 5 | FZ19: =DF19+FX19-FY19 -> 65 | GC19: =GA19+GB19 -> 0 | GE19: =DK19+GC19-GD19 -> 0 | GH19: 5 | GJ19: =+FZ19+GH19-GI19 -> 70 | GM19: =GK19+GL19 -> 0 | GO19: =+GE19+GM19-GN19 -> 0 | GT19: =GJ19+GR19-GS19 -> 70 | GW19: =GU19+GV19 -> 0 | GY19: =+GO19+GW19-GX19 -> 0
A20: 10 | B20: 10 | C20: 10 | D20: MOSCUY ALVAREZ MONICA AZUCENA | E20: 0 | F20: 10 | H20: =E20+F20-G20 -> 10 | M20: =+I20+J20-L20 -> 0 | Q20: 5 | S20: =H20+Q20-R20 -> 15 | V20: =T20+U20 -> 0 | X20: =M20+T20+U20-W20 -> 0 | AB20: 5 | AD20: =S20+AB20-AC20 -> 20 | AG20: =AE20+AF20 -> 0 | AI20: =X20+AE20+AF20-AH20 -> 0 | AL20: 5 | AN20: =AD20+AL20-AM20 -> 25 | AQ20: =AO20+AP20 -> 0 | AS20: =AI20+AO20+AP20-AR20 -> 0 | AV20: 5 | AX20: =AN20+AV20-AW20 -> 30 | BA20: =AY20+AZ20 -> 0 | BC20: =AS20+AY20+AZ20-BB20 -> 0 | BF20: 5 | BH20: =AX20+BF20-BG20 -> 35 | BK20: =BI20+BJ20 -> 0 | BM20: =BC20+BI20+BJ20-BL20 -> 0 | BP20: 5 | BR20: =BH20+BP20-BQ20 -> 40 | BU20: =BS20+BT20 -> 0 | BW20: =BM20+BS20+BT20-BV20 -> 0 | BZ20: 5 | CB20: =BR20+BZ20-CA20 -> 45 | CC20: 100 | CD20: 15 | CE20: =CC20+CD20 -> 115 | CG20: =BW20+CC20+CD20-CF20 -> 115 | CJ20: 5 | CL20: =CB20+CJ20-CK20 -> 50 | CO20: =CM20+CN20 -> 0 | CP20: 5 | CQ20: =CG20+CM20+CN20-CP20 -> 110 | CT20: 5 | CV20: =CL20+CT20-CU20 -> 55 | CY20: =CW20+CX20 -> 0 | CZ20: 5 | DA20: =CQ20+CW20+CX20-CZ20 -> 105 | DD20: 5 | DF20: =CV20+DD20-DE20 -> 60 | DI20: =DG20+DH20 -> 0 | DJ20: 105 | DK20: =DA20+DG20+DH20-DJ20 -> 0 | DN20: 10 | DP20: =DF20+DN20-DO20 -> 70 | DS20: =DQ20+DR20 -> 0 | DU20: =DK20+DQ20+DR20-DT20 -> 0 | DZ20: =DP20+DX20-DY20 -> 70 | EC20: =EA20+EB20 -> 0 | EE20: =DU20+EA20+EB20-ED20 -> 0 | EJ20: =DZ20+EH20-EI20 -> 70 | EM20: =EK20+EL20 -> 0 | EO20: =EE20+EK20+EL20-EN20 -> 0 | ET20: =EJ20+ER20-ES20 -> 70 | EW20: =EU20+EV20 -> 0 | EY20: =EO20+EU20+EV20-EX20 -> 0 | FD20: =ET20+FB20-FC20 -> 70 | FG20: =FE20+FF20 -> 0 | FI20: =EY20+FE20+FF20-FH20 -> 0 | FN20: =FD20+FL20-FM20 -> 70 | FQ20: =FO20+FP20 -> 0 | FS20: =FI20+FO20+FP20-FR20 -> 0 | FX20: 5 | FZ20: =DF20+FX20-FY20 -> 65 | GC20: =GA20+GB20 -> 0 | GE20: =DK20+GC20-GD20 -> 0 | GH20: 5 | GJ20: =+FZ20+GH20-GI20 -> 70 | GM20: =GK20+GL20 -> 0 | GO20: =+GE20+GM20-GN20 -> 0 | GT20: =GJ20+GR20-GS20 -> 70 | GW20: =GU20+GV20 -> 0 | GY20: =+GO20+GW20-GX20 -> 0
A21: 11 | B21: 11 | C21: 11 | D21: MOSCUY CULQUI MARIA NORMA | E21: 0 | F21: 10 | H21: =E21+F21-G21 -> 10 | M21: =+I21+J21-L21 -> 0 | Q21: 5 | S21: =H21+Q21-R21 -> 15 | V21: =T21+U21 -> 0 | X21: =M21+T21+U21-W21 -> 0 | AB21: 5 | AD21: =S21+AB21-AC21 -> 20 | AG21: =AE21+AF21 -> 0 | AI21: =X21+AE21+AF21-AH21 -> 0 | AL21: 5 | AN21: =AD21+AL21-AM21 -> 25 | AO21: 100 | AP21: 15 | AQ21: =AO21+AP21 -> 115 | AS21: =AI21+AO21+AP21-AR21 -> 115 | AV21: 5 | AX21: =AN21+AV21-AW21 -> 30 | BA21: =AY21+AZ21 -> 0 | BB21: 5 | BC21: =AS21+AY21+AZ21-BB21 -> 110 | BF21: 5 | BH21: =AX21+BF21-BG21 -> 35 | BK21: =BI21+BJ21 -> 0 | BL21: 5 | BM21: =BC21+BI21+BJ21-BL21 -> 105 | BP21: 5 | BR21: =BH21+BP21-BQ21 -> 40 | BU21: =BS21+BT21 -> 0 | BV21: 105 | BW21: =BM21+BS21+BT21-BV21 -> 0 | BZ21: 5 | CB21: =BR21+BZ21-CA21 -> 45 | CC21: 100 | CD21: 15 | CE21: =CC21+CD21 -> 115 | CG21: =BW21+CC21+CD21-CF21 -> 115 | CJ21: 5 | CL21: =CB21+CJ21-CK21 -> 50 | CO21: =CM21+CN21 -> 0 | CP21: 5 | CQ21: =CG21+CM21+CN21-CP21 -> 110 | CT21: 5 | CV21: =CL21+CT21-CU21 -> 55 | CY21: =CW21+CX21 -> 0 | CZ21: 5 | DA21: =CQ21+CW21+CX21-CZ21 -> 105 | DD21: 5 | DF21: =CV21+DD21-DE21 -> 60 | DG21: 100 | DH21: 15 | DI21: =DG21+DH21 -> 115 | DJ21: 105 | DK21: =DA21+DG21+DH21-DJ21 -> 115 | DN21: 10.4 | DP21: =DF21+DN21-DO21 -> 70.4 | DS21: =DQ21+DR21 -> 0 | DT21: 124.6 | DU21: =DK21+DQ21+DR21-DT21 -> -9.6 | DZ21: =DP21+DX21-DY21 -> 70.4 | EC21: =EA21+EB21 -> 0 | EE21: =DU21+EA21+EB21-ED21 -> -9.6 | EJ21: =DZ21+EH21-EI21 -> 70.4 | EM21: =EK21+EL21 -> 0 | EO21: =EE21+EK21+EL21-EN21 -> -9.6 | ET21: =EJ21+ER21-ES21 -> 70.4 | EW21: =EU21+EV21 -> 0 | EY21: =EO21+EU21+EV21-EX21 -> -9.6 | FD21: =ET21+FB21-FC21 -> 70.4 | FG21: =FE21+FF21 -> 0 | FI21: =EY21+FE21+FF21-FH21 -> -9.6 | FN21: =FD21+FL21-FM21 -> 70.4 | FQ21: =FO21+FP21 -> 0 | FS21: =FI21+FO21+FP21-FR21 -> -9.6 | FX21: 5 | FZ21: =DF21+FX21-FY21 -> 65 | GC21: =GA21+GB21 -> 0 | GD21: 5 | GE21: =DK21+GC21-GD21 -> 110 | GH21: 5 | GJ21: =+FZ21+GH21-GI21 -> 70 | GM21: =GK21+GL21 -> 0 | GO21: =+GE21+GM21-GN21 -> 110 | GT21: =GJ21+GR21-GS21 -> 70 | GW21: =GU21+GV21 -> 0 | GY21: =+GO21+GW21-GX21 -> 110
A22: 12 | B22: 12 | C22: 12 | D22: MOSCUY ALVAREZ BLANCA ROCIO | F22: 10 | H22: =E22+F22-G22 -> 10 | M22: =+I22+J22-L22 -> 0 | S22: =H22+Q22-R22 -> 10 | V22: =T22+U22 -> 0 | X22: =M22+T22+U22-W22 -> 0 | AB22: 10 | AD22: =S22+AB22-AC22 -> 20 | AE22: 100 | AF22: 15 | AG22: =AE22+AF22 -> 115 | AI22: =X22+AE22+AF22-AH22 -> 115 | AL22: 5 | AN22: =AD22+AL22-AM22 -> 25 | AQ22: =AO22+AP22 -> 0 | AR22: 5 | AS22: =AI22+AO22+AP22-AR22 -> 110 | AV22: 5 | AX22: =AN22+AV22-AW22 -> 30 | BA22: =AY22+AZ22 -> 0 | BB22: 5 | BC22: =AS22+AY22+AZ22-BB22 -> 105 | BF22: 5 | BH22: =AX22+BF22-BG22 -> 35 | BI22: 200 | BJ22: 30 | BK22: =BI22+BJ22 -> 230 | BL22: 105 | BM22: =BC22+BI22+BJ22-BL22 -> 230 | BP22: 5 | BR22: =BH22+BP22-BQ22 -> 40 | BU22: =BS22+BT22 -> 0 | BV22: 10 | BW22: =BM22+BS22+BT22-BV22 -> 220 | BZ22: 5 | CB22: =BR22+BZ22-CA22 -> 45 | CE22: =CC22+CD22 -> 0 | CF22: 10 | CG22: =BW22+CC22+CD22-CF22 -> 210 | CJ22: 5 | CL22: =CB22+CJ22-CK22 -> 50 | CM22: 200 | CN22: 30 | CO22: =CM22+CN22 -> 230 | CP22: 210 | CQ22: =CG22+CM22+CN22-CP22 -> 230 | CT22: 5 | CV22: =CL22+CT22-CU22 -> 55 | CY22: =CW22+CX22 -> 0 | CZ22: 10 | DA22: =CQ22+CW22+CX22-CZ22 -> 220 | DD22: 5 | DF22: =CV22+DD22-DE22 -> 60 | DI22: =DG22+DH22 -> 0 | DJ22: 10 | DK22: =DA22+DG22+DH22-DJ22 -> 210 | DN22: 10 | DP22: =DF22+DN22-DO22 -> 70 | DS22: =DQ22+DR22 -> 0 | DT22: 140 | DU22: =DK22+DQ22+DR22-DT22 -> 70 | DZ22: =DP22+DX22-DY22 -> 70 | EC22: =EA22+EB22 -> 0 | EE22: =DU22+EA22+EB22-ED22 -> 70 | EJ22: =DZ22+EH22-EI22 -> 70 | EM22: =EK22+EL22 -> 0 | EO22: =EE22+EK22+EL22-EN22 -> 70 | ET22: =EJ22+ER22-ES22 -> 70 | EW22: =EU22+EV22 -> 0 | EY22: =EO22+EU22+EV22-EX22 -> 70 | FD22: =ET22+FB22-FC22 -> 70 | FG22: =FE22+FF22 -> 0 | FI22: =EY22+FE22+FF22-FH22 -> 70 | FN22: =FD22+FL22-FM22 -> 70 | FQ22: =FO22+FP22 -> 0 | FS22: =FI22+FO22+FP22-FR22 -> 70 | FX22: 5 | FZ22: =DF22+FX22-FY22 -> 65 | GA22: 200 | GB22: 30 | GC22: =GA22+GB22 -> 230 | GD22: 210 | GE22: =DK22+GC22-GD22 -> 230 | GH22: 5 | GJ22: =+FZ22+GH22-GI22 -> 70 | GM22: =GK22+GL22 -> 0 | GO22: =+GE22+GM22-GN22 -> 230 | GT22: =GJ22+GR22-GS22 -> 70 | GW22: =GU22+GV22 -> 0 | GY22: =+GO22+GW22-GX22 -> 230
A23: 13 | B23: 13 | C23: 13 | D23: MOSCUY CHACON VICTOR RODOLFO | E23: 0 | F23: 10 | H23: =E23+F23-G23 -> 10 | M23: =+I23+J23-L23 -> 0 | Q23: 5 | S23: =H23+Q23-R23 -> 15 | V23: =T23+U23 -> 0 | X23: =M23+T23+U23-W23 -> 0 | AB23: 5 | AD23: =S23+AB23-AC23 -> 20 | AG23: =AE23+AF23 -> 0 | AI23: =X23+AE23+AF23-AH23 -> 0 | AL23: 5 | AN23: =AD23+AL23-AM23 -> 25 | AQ23: =AO23+AP23 -> 0 | AS23: =AI23+AO23+AP23-AR23 -> 0 | AV23: 5 | AX23: =AN23+AV23-AW23 -> 30 | BA23: =AY23+AZ23 -> 0 | BC23: =AS23+AY23+AZ23-BB23 -> 0 | BF23: 5 | BH23: =AX23+BF23-BG23 -> 35 | BK23: =BI23+BJ23 -> 0 | BM23: =BC23+BI23+BJ23-BL23 -> 0 | BP23: 5 | BR23: =BH23+BP23-BQ23 -> 40 | BU23: =BS23+BT23 -> 0 | BW23: =BM23+BS23+BT23-BV23 -> 0 | BZ23: 5 | CB23: =BR23+BZ23-CA23 -> 45 | CE23: =CC23+CD23 -> 0 | CG23: =BW23+CC23+CD23-CF23 -> 0 | CJ23: 5 | CL23: =CB23+CJ23-CK23 -> 50 | CO23: =CM23+CN23 -> 0 | CQ23: =CG23+CM23+CN23-CP23 -> 0 | CT23: 5 | CV23: =CL23+CT23-CU23 -> 55 | CY23: =CW23+CX23 -> 0 | DA23: =CQ23+CW23+CX23-CZ23 -> 0 | DD23: 5 | DF23: =CV23+DD23-DE23 -> 60 | DG23: 100 | DH23: 15 | DI23: =DG23+DH23 -> 115 | DK23: =DA23+DG23+DH23-DJ23 -> 115 | DN23: 10 | DP23: =DF23+DN23-DO23 -> 70 | DQ23: 900 | DR23: 162 | DS23: =DQ23+DR23 -> 1062 | DU23: =DK23+DQ23+DR23-DT23 -> 1177 | DZ23: =DP23+DX23-DY23 -> 70 | EC23: =EA23+EB23 -> 0 | EE23: =DU23+EA23+EB23-ED23 -> 1177 | EJ23: =DZ23+EH23-EI23 -> 70 | EM23: =EK23+EL23 -> 0 | EO23: =EE23+EK23+EL23-EN23 -> 1177 | ET23: =EJ23+ER23-ES23 -> 70 | EW23: =EU23+EV23 -> 0 | EY23: =EO23+EU23+EV23-EX23 -> 1177 | FD23: =ET23+FB23-FC23 -> 70 | FG23: =FE23+FF23 -> 0 | FI23: =EY23+FE23+FF23-FH23 -> 1177 | FN23: =FD23+FL23-FM23 -> 70 | FQ23: =FO23+FP23 -> 0 | FS23: =FI23+FO23+FP23-FR23 -> 1177 | FX23: 5 | FZ23: =DF23+FX23-FY23 -> 65 | GC23: =GA23+GB23 -> 0 | GD23: 5 | GE23: =DK23+GC23-GD23 -> 110 | GH23: 5 | GJ23: =+FZ23+GH23-GI23 -> 70 | GM23: =GK23+GL23 -> 0 | GO23: =+GE23+GM23-GN23 -> 110 | GT23: =GJ23+GR23-GS23 -> 70 | GW23: =GU23+GV23 -> 0 | GY23: =+GO23+GW23-GX23 -> 110
B24: 14 | C24: 14 | D24: PANCHI HERRERA ANAHI ALEJANDRA | E24: 0 | F24: 10 | H24: =E24+F24-G24 -> 10 | M24: =+I24+J24-L24 -> 0 | Q24: 5 | S24: =H24+Q24-R24 -> 15 | V24: =T24+U24 -> 0 | X24: =M24+T24+U24-W24 -> 0 | AB24: 5 | AD24: =S24+AB24-AC24 -> 20 | AG24: =AE24+AF24 -> 0 | AI24: =X24+AE24+AF24-AH24 -> 0 | AL24: 5 | AN24: =AD24+AL24-AM24 -> 25 | AQ24: =AO24+AP24 -> 0 | AS24: =AI24+AO24+AP24-AR24 -> 0 | AV24: 5 | AX24: =AN24+AV24-AW24 -> 30 | BA24: =AY24+AZ24 -> 0 | BC24: =AS24+AY24+AZ24-BB24 -> 0 | BF24: 5 | BH24: =AX24+BF24-BG24 -> 35 | BK24: =BI24+BJ24 -> 0 | BM24: =BC24+BI24+BJ24-BL24 -> 0 | BP24: 5 | BR24: =BH24+BP24-BQ24 -> 40 | BU24: =BS24+BT24 -> 0 | BW24: =BM24+BS24+BT24-BV24 -> 0 | BZ24: 5 | CB24: =BR24+BZ24-CA24 -> 45 | CE24: =CC24+CD24 -> 0 | CG24: =BW24+CC24+CD24-CF24 -> 0 | CJ24: 5 | CL24: =CB24+CJ24-CK24 -> 50 | CO24: =CM24+CN24 -> 0 | CQ24: =CG24+CM24+CN24-CP24 -> 0 | CT24: 5 | CV24: =CL24+CT24-CU24 -> 55 | CY24: =CW24+CX24 -> 0 | DA24: =CQ24+CW24+CX24-CZ24 -> 0 | DD24: 5 | DF24: =CV24+DD24-DE24 -> 60 | DI24: =DG24+DH24 -> 0 | DK24: =DA24+DG24+DH24-DJ24 -> 0 | DN24: 60 | DP24: =DF24+DN24-DO24 -> 120 | DS24: =DQ24+DR24 -> 0 | DU24: =DK24+DQ24+DR24-DT24 -> 0 | DZ24: =DP24+DX24-DY24 -> 120 | EC24: =EA24+EB24 -> 0 | EE24: =DU24+EA24+EB24-ED24 -> 0 | EJ24: =DZ24+EH24-EI24 -> 120 | EM24: =EK24+EL24 -> 0 | EO24: =EE24+EK24+EL24-EN24 -> 0 | ET24: =EJ24+ER24-ES24 -> 120 | EW24: =EU24+EV24 -> 0 | EY24: =EO24+EU24+EV24-EX24 -> 0 | FD24: =ET24+FB24-FC24 -> 120 | FG24: =FE24+FF24 -> 0 | FI24: =EY24+FE24+FF24-FH24 -> 0 | FN24: =FD24+FL24-FM24 -> 120 | FQ24: =FO24+FP24 -> 0 | FS24: =FI24+FO24+FP24-FR24 -> 0 | FX24: 5 | FZ24: =DF24+FX24-FY24 -> 65 | GC24: =GA24+GB24 -> 0 | GE24: =DK24+GC24-GD24 -> 0 | GH24: 5 | GJ24: =+FZ24+GH24-GI24 -> 70 | GK24: 100 | GL24: 15 | GM24: =GK24+GL24 -> 115 | GO24: =+GE24+GM24-GN24 -> 115 | GT24: =GJ24+GR24-GS24 -> 70 | GW24: =GU24+GV24 -> 0 | GY24: =+GO24+GW24-GX24 -> 115
A25: 15 | B25: 15 | C25: 15 | D25: PEÑAFIEL CHICAIZA CARLOS WLADIMIR | E25: 0 | F25: 10 | H25: =E25+F25-G25 -> 10 | M25: =+I25+J25-L25 -> 0 | Q25: 5 | S25: =H25+Q25-R25 -> 15 | T25: 100 | U25: 15 | V25: =T25+U25 -> 115 | X25: =M25+T25+U25-W25 -> 115 | AB25: 5 | AD25: =S25+AB25-AC25 -> 20 | AG25: =AE25+AF25 -> 0 | AH25: 5 | AI25: =X25+AE25+AF25-AH25 -> 110 | AL25: 5 | AN25: =AD25+AL25-AM25 -> 25 | AQ25: =AO25+AP25 -> 0 | AR25: 5 | AS25: =AI25+AO25+AP25-AR25 -> 105 | AV25: 5 | AX25: =AN25+AV25-AW25 -> 30 | AY25: 100 | AZ25: 15 | BA25: =AY25+AZ25 -> 115 | BB25: 105 | BC25: =AS25+AY25+AZ25-BB25 -> 115 | BF25: 5 | BH25: =AX25+BF25-BG25 -> 35 | BK25: =BI25+BJ25 -> 0 | BL25: 5 | BM25: =BC25+BI25+BJ25-BL25 -> 110 | BP25: 5 | BR25: =BH25+BP25-BQ25 -> 40 | BU25: =BS25+BT25 -> 0 | BV25: 5 | BW25: =BM25+BS25+BT25-BV25 -> 105 | BZ25: 5 | CB25: =BR25+BZ25-CA25 -> 45 | CE25: =CC25+CD25 -> 0 | CF25: 105 | CG25: =BW25+CC25+CD25-CF25 -> 0 | CJ25: 5 | CL25: =CB25+CJ25-CK25 -> 50 | CO25: =CM25+CN25 -> 0 | CQ25: =CG25+CM25+CN25-CP25 -> 0 | CT25: 5 | CV25: =CL25+CT25-CU25 -> 55 | CY25: =CW25+CX25 -> 0 | DA25: =CQ25+CW25+CX25-CZ25 -> 0 | DD25: 5 | DF25: =CV25+DD25-DE25 -> 60 | DI25: =DG25+DH25 -> 0 | DK25: =DA25+DG25+DH25-DJ25 -> 0 | DN25: 10.84 | DP25: =DF25+DN25-DO25 -> 70.84 | DS25: =DQ25+DR25 -> 0 | DT25: 49.16 | DU25: =DK25+DQ25+DR25-DT25 -> -49.16 | DZ25: =DP25+DX25-DY25 -> 70.84 | EC25: =EA25+EB25 -> 0 | EE25: =DU25+EA25+EB25-ED25 -> -49.16 | EJ25: =DZ25+EH25-EI25 -> 70.84 | EM25: =EK25+EL25 -> 0 | EO25: =EE25+EK25+EL25-EN25 -> -49.16 | ET25: =EJ25+ER25-ES25 -> 70.84 | EW25: =EU25+EV25 -> 0 | EY25: =EO25+EU25+EV25-EX25 -> -49.16 | FD25: =ET25+FB25-FC25 -> 70.84 | FG25: =FE25+FF25 -> 0 | FI25: =EY25+FE25+FF25-FH25 -> -49.16 | FN25: =FD25+FL25-FM25 -> 70.84 | FQ25: =FO25+FP25 -> 0 | FS25: =FI25+FO25+FP25-FR25 -> -49.16 | FX25: 5 | FZ25: =DF25+FX25-FY25 -> 65 | GA25: 200 | GB25: 30 | GC25: =GA25+GB25 -> 230 | GE25: =DK25+GC25-GD25 -> 230 | GH25: 5 | GJ25: =+FZ25+GH25-GI25 -> 70 | GM25: =GK25+GL25 -> 0 | GO25: =+GE25+GM25-GN25 -> 230 | GT25: =GJ25+GR25-GS25 -> 70 | GW25: =GU25+GV25 -> 0 | GY25: =+GO25+GW25-GX25 -> 230
A26: 16 | B26: 16 | C26: 16 | D26: PEÑAFIEL CHICAIZA MAURICIO CRISTOBAL | E26: 0 | F26: 10 | H26: =E26+F26-G26 -> 10 | M26: =+I26+J26-L26 -> 0 | Q26: 5 | S26: =H26+Q26-R26 -> 15 | V26: =T26+U26 -> 0 | X26: =M26+T26+U26-W26 -> 0 | AB26: 5 | AD26: =S26+AB26-AC26 -> 20 | AG26: =AE26+AF26 -> 0 | AI26: =X26+AE26+AF26-AH26 -> 0 | AL26: 5 | AN26: =AD26+AL26-AM26 -> 25 | AQ26: =AO26+AP26 -> 0 | AS26: =AI26+AO26+AP26-AR26 -> 0 | AV26: 5 | AX26: =AN26+AV26-AW26 -> 30 | BA26: =AY26+AZ26 -> 0 | BC26: =AS26+AY26+AZ26-BB26 -> 0 | BF26: 5 | BH26: =AX26+BF26-BG26 -> 35 | BK26: =BI26+BJ26 -> 0 | BM26: =BC26+BI26+BJ26-BL26 -> 0 | BP26: 5 | BR26: =BH26+BP26-BQ26 -> 40 | BU26: =BS26+BT26 -> 0 | BW26: =BM26+BS26+BT26-BV26 -> 0 | BZ26: 5 | CB26: =BR26+BZ26-CA26 -> 45 | CE26: =CC26+CD26 -> 0 | CG26: =BW26+CC26+CD26-CF26 -> 0 | CJ26: 5 | CL26: =CB26+CJ26-CK26 -> 50 | CO26: =CM26+CN26 -> 0 | CQ26: =CG26+CM26+CN26-CP26 -> 0 | CT26: 5 | CV26: =CL26+CT26-CU26 -> 55 | CY26: =CW26+CX26 -> 0 | DA26: =CQ26+CW26+CX26-CZ26 -> 0 | DD26: 5 | DF26: =CV26+DD26-DE26 -> 60 | DG26: 300 | DH26: 45 | DI26: =DG26+DH26 -> 345 | DK26: =DA26+DG26+DH26-DJ26 -> 345 | DN26: 10 | DP26: =DF26+DN26-DO26 -> 70 | DS26: =DQ26+DR26 -> 0 | DU26: =DK26+DQ26+DR26-DT26 -> 345 | DZ26: =DP26+DX26-DY26 -> 70 | EC26: =EA26+EB26 -> 0 | EE26: =DU26+EA26+EB26-ED26 -> 345 | EJ26: =DZ26+EH26-EI26 -> 70 | EM26: =EK26+EL26 -> 0 | EO26: =EE26+EK26+EL26-EN26 -> 345 | ET26: =EJ26+ER26-ES26 -> 70 | EW26: =EU26+EV26 -> 0 | EY26: =EO26+EU26+EV26-EX26 -> 345 | FD26: =ET26+FB26-FC26 -> 70 | FG26: =FE26+FF26 -> 0 | FI26: =EY26+FE26+FF26-FH26 -> 345 | FN26: =FD26+FL26-FM26 -> 70 | FQ26: =FO26+FP26 -> 0 | FS26: =FI26+FO26+FP26-FR26 -> 345 | FX26: 5 | FZ26: =DF26+FX26-FY26 -> 65 | GC26: =GA26+GB26 -> 0 | GD26: 15 | GE26: =DK26+GC26-GD26 -> 330 | GH26: 5 | GJ26: =+FZ26+GH26-GI26 -> 70 | GM26: =GK26+GL26 -> 0 | GO26: =+GE26+GM26-GN26 -> 330 | GT26: =GJ26+GR26-GS26 -> 70 | GW26: =GU26+GV26 -> 0 | GY26: =+GO26+GW26-GX26 -> 330
A27: 17 | B27: 17 | C27: 17 | D27: PRUNA CANDO JUAN DAVID | F27: 10 | H27: =E27+F27-G27 -> 10 | M27: =+I27+J27-L27 -> 0 | Q27: 5 | S27: =H27+Q27-R27 -> 15 | V27: =T27+U27 -> 0 | X27: =M27+T27+U27-W27 -> 0 | AB27: 5 | AD27: =S27+AB27-AC27 -> 20 | AG27: =AE27+AF27 -> 0 | AI27: =X27+AE27+AF27-AH27 -> 0 | AL27: 5 | AN27: =AD27+AL27-AM27 -> 25 | AQ27: =AO27+AP27 -> 0 | AS27: =AI27+AO27+AP27-AR27 -> 0 | AV27: 5 | AX27: =AN27+AV27-AW27 -> 30 | BA27: =AY27+AZ27 -> 0 | BC27: =AS27+AY27+AZ27-BB27 -> 0 | BF27: 5 | BH27: =AX27+BF27-BG27 -> 35 | BK27: =BI27+BJ27 -> 0 | BM27: =BC27+BI27+BJ27-BL27 -> 0 | BP27: 5 | BR27: =BH27+BP27-BQ27 -> 40 | BU27: =BS27+BT27 -> 0 | BW27: =BM27+BS27+BT27-BV27 -> 0 | BZ27: 5 | CB27: =BR27+BZ27-CA27 -> 45 | CE27: =CC27+CD27 -> 0 | CG27: =BW27+CC27+CD27-CF27 -> 0 | CJ27: 5 | CL27: =CB27+CJ27-CK27 -> 50 | CO27: =CM27+CN27 -> 0 | CQ27: =CG27+CM27+CN27-CP27 -> 0 | CT27: 5 | CV27: =CL27+CT27-CU27 -> 55 | CY27: =CW27+CX27 -> 0 | DA27: =CQ27+CW27+CX27-CZ27 -> 0 | DD27: 5 | DF27: =CV27+DD27-DE27 -> 60 | DI27: =DG27+DH27 -> 0 | DK27: =DA27+DG27+DH27-DJ27 -> 0 | DP27: =DF27+DN27-DO27 -> 60 | DS27: =DQ27+DR27 -> 0 | DU27: =DK27+DQ27+DR27-DT27 -> 0 | DZ27: =DP27+DX27-DY27 -> 60 | EC27: =EA27+EB27 -> 0 | EE27: =DU27+EA27+EB27-ED27 -> 0 | EJ27: =DZ27+EH27-EI27 -> 60 | EM27: =EK27+EL27 -> 0 | EO27: =EE27+EK27+EL27-EN27 -> 0 | ET27: =EJ27+ER27-ES27 -> 60 | EW27: =EU27+EV27 -> 0 | EY27: =EO27+EU27+EV27-EX27 -> 0 | FD27: =ET27+FB27-FC27 -> 60 | FG27: =FE27+FF27 -> 0 | FI27: =EY27+FE27+FF27-FH27 -> 0 | FN27: =FD27+FL27-FM27 -> 60 | FQ27: =FO27+FP27 -> 0 | FS27: =FI27+FO27+FP27-FR27 -> 0 | FX27: 5 | FZ27: =DF27+FX27-FY27 -> 65 | GA27: 100 | GB27: 15 | GC27: =GA27+GB27 -> 115 | GE27: =DK27+GC27-GD27 -> 115 | GH27: 5 | GJ27: =+FZ27+GH27-GI27 -> 70 | GM27: =GK27+GL27 -> 0 | GO27: =+GE27+GM27-GN27 -> 115 | GT27: =GJ27+GR27-GS27 -> 70 | GW27: =GU27+GV27 -> 0 | GY27: =+GO27+GW27-GX27 -> 115
A28: 19 | B28: 18 | C28: 18 | D28: PRUNA SINCHIGUANO KELLY MONSERRATH | E28: 0 | F28: 10 | H28: =E28+F28-G28 -> 10 | M28: =+I28+J28-L28 -> 0 | Q28: 5 | S28: =H28+Q28-R28 -> 15 | V28: =T28+U28 -> 0 | X28: =M28+T28+U28-W28 -> 0 | AB28: 5 | AD28: =S28+AB28-AC28 -> 20 | AG28: =AE28+AF28 -> 0 | AI28: =X28+AE28+AF28-AH28 -> 0 | AL28: 5 | AN28: =AD28+AL28-AM28 -> 25 | AQ28: =AO28+AP28 -> 0 | AS28: =AI28+AO28+AP28-AR28 -> 0 | AV28: 5 | AX28: =AN28+AV28-AW28 -> 30 | BA28: =AY28+AZ28 -> 0 | BC28: =AS28+AY28+AZ28-BB28 -> 0 | BF28: 5 | BH28: =AX28+BF28-BG28 -> 35 | BK28: =BI28+BJ28 -> 0 | BM28: =BC28+BI28+BJ28-BL28 -> 0 | BP28: 5 | BR28: =BH28+BP28-BQ28 -> 40 | BU28: =BS28+BT28 -> 0 | BW28: =BM28+BS28+BT28-BV28 -> 0 | BZ28: 5 | CB28: =BR28+BZ28-CA28 -> 45 | CE28: =CC28+CD28 -> 0 | CG28: =BW28+CC28+CD28-CF28 -> 0 | CJ28: 5 | CL28: =CB28+CJ28-CK28 -> 50 | CO28: =CM28+CN28 -> 0 | CQ28: =CG28+CM28+CN28-CP28 -> 0 | CT28: 5 | CV28: =CL28+CT28-CU28 -> 55 | CY28: =CW28+CX28 -> 0 | DA28: =CQ28+CW28+CX28-CZ28 -> 0 | DD28: 5 | DF28: =CV28+DD28-DE28 -> 60 | DG28: 100 | DH28: 15 | DI28: =DG28+DH28 -> 115 | DK28: =DA28+DG28+DH28-DJ28 -> 115 | DN28: 5 | DP28: =DF28+DN28-DO28 -> 65 | DS28: =DQ28+DR28 -> 0 | DU28: =DK28+DQ28+DR28-DT28 -> 115 | DZ28: =DP28+DX28-DY28 -> 65 | EC28: =EA28+EB28 -> 0 | EE28: =DU28+EA28+EB28-ED28 -> 115 | EJ28: =DZ28+EH28-EI28 -> 65 | EM28: =EK28+EL28 -> 0 | EO28: =EE28+EK28+EL28-EN28 -> 115 | ET28: =EJ28+ER28-ES28 -> 65 | EW28: =EU28+EV28 -> 0 | EY28: =EO28+EU28+EV28-EX28 -> 115 | FD28: =ET28+FB28-FC28 -> 65 | FG28: =FE28+FF28 -> 0 | FI28: =EY28+FE28+FF28-FH28 -> 115 | FN28: =FD28+FL28-FM28 -> 65 | FQ28: =FO28+FP28 -> 0 | FS28: =FI28+FO28+FP28-FR28 -> 115 | FX28: 5 | FZ28: =DF28+FX28-FY28 -> 65 | GC28: =GA28+GB28 -> 0 | GD28: 5 | GE28: =DK28+GC28-GD28 -> 110 | GH28: 5 | GJ28: =+FZ28+GH28-GI28 -> 70 | GM28: =GK28+GL28 -> 0 | GO28: =+GE28+GM28-GN28 -> 110 | GT28: =GJ28+GR28-GS28 -> 70 | GW28: =GU28+GV28 -> 0 | GY28: =+GO28+GW28-GX28 -> 110
A29: 23 | B29: 19 | C29: 19 | D29: PRUNA MOSCUY LEIDY GISSELA | F29: 10 | H29: =E29+F29-G29 -> 10 | M29: =+I29+J29-L29 -> 0 | S29: =H29+Q29-R29 -> 10 | V29: =T29+U29 -> 0 | X29: =M29+T29+U29-W29 -> 0 | AD29: =S29+AB29-AC29 -> 10 | AG29: =AE29+AF29 -> 0 | AI29: =X29+AE29+AF29-AH29 -> 0 | AL29: 15 | AN29: =AD29+AL29-AM29 -> 25 | AQ29: =AO29+AP29 -> 0 | AS29: =AI29+AO29+AP29-AR29 -> 0 | AV29: 5 | AX29: =AN29+AV29-AW29 -> 30 | BA29: =AY29+AZ29 -> 0 | BC29: =AS29+AY29+AZ29-BB29 -> 0 | BF29: 5 | BH29: =AX29+BF29-BG29 -> 35 | BK29: =BI29+BJ29 -> 0 | BM29: =BC29+BI29+BJ29-BL29 -> 0 | BP29: 5 | BR29: =BH29+BP29-BQ29 -> 40 | BU29: =BS29+BT29 -> 0 | BW29: =BM29+BS29+BT29-BV29 -> 0 | BZ29: 5 | CB29: =BR29+BZ29-CA29 -> 45 | CE29: =CC29+CD29 -> 0 | CG29: =BW29+CC29+CD29-CF29 -> 0 | CJ29: 5 | CL29: =CB29+CJ29-CK29 -> 50 | CO29: =CM29+CN29 -> 0 | CQ29: =CG29+CM29+CN29-CP29 -> 0 | CT29: 5 | CV29: =CL29+CT29-CU29 -> 55 | CY29: =CW29+CX29 -> 0 | DA29: =CQ29+CW29+CX29-CZ29 -> 0 | DD29: 5 | DF29: =CV29+DD29-DE29 -> 60 | DG29: 100 | DH29: 15 | DI29: =DG29+DH29 -> 115 | DK29: =DA29+DG29+DH29-DJ29 -> 115 | DN29: 5 | DP29: =DF29+DN29-DO29 -> 65 | DS29: =DQ29+DR29 -> 0 | DU29: =DK29+DQ29+DR29-DT29 -> 115 | DZ29: =DP29+DX29-DY29 -> 65 | EC29: =EA29+EB29 -> 0 | EE29: =DU29+EA29+EB29-ED29 -> 115 | EJ29: =DZ29+EH29-EI29 -> 65 | EM29: =EK29+EL29 -> 0 | EO29: =EE29+EK29+EL29-EN29 -> 115 | ET29: =EJ29+ER29-ES29 -> 65 | EW29: =EU29+EV29 -> 0 | EY29: =EO29+EU29+EV29-EX29 -> 115 | FD29: =ET29+FB29-FC29 -> 65 | FG29: =FE29+FF29 -> 0 | FI29: =EY29+FE29+FF29-FH29 -> 115 | FN29: =FD29+FL29-FM29 -> 65 | FQ29: =FO29+FP29 -> 0 | FS29: =FI29+FO29+FP29-FR29 -> 115 | FX29: 5 | FZ29: =DF29+FX29-FY29 -> 65 | GC29: =GA29+GB29 -> 0 | GD29: 5 | GE29: =DK29+GC29-GD29 -> 110 | GH29: 5 | GJ29: =+FZ29+GH29-GI29 -> 70 | GM29: =GK29+GL29 -> 0 | GO29: =+GE29+GM29-GN29 -> 110 | GT29: =GJ29+GR29-GS29 -> 70 | GW29: =GU29+GV29 -> 0 | GY29: =+GO29+GW29-GX29 -> 110
A30: 24 | B30: 20 | C30: 20 | D30: PRUNA CANDO LIZARDO RAUL | E30: 0 | F30: 10 | H30: =E30+F30-G30 -> 10 | M30: =+I30+J30-L30 -> 0 | Q30: 5 | S30: =H30+Q30-R30 -> 15 | V30: =T30+U30 -> 0 | X30: =M30+T30+U30-W30 -> 0 | AB30: 5 | AD30: =S30+AB30-AC30 -> 20 | AG30: =AE30+AF30 -> 0 | AI30: =X30+AE30+AF30-AH30 -> 0 | AL30: 5 | AN30: =AD30+AL30-AM30 -> 25 | AQ30: =AO30+AP30 -> 0 | AS30: =AI30+AO30+AP30-AR30 -> 0 | AV30: 5 | AX30: =AN30+AV30-AW30 -> 30 | BA30: =AY30+AZ30 -> 0 | BC30: =AS30+AY30+AZ30-BB30 -> 0 | BF30: 5 | BH30: =AX30+BF30-BG30 -> 35 | BK30: =BI30+BJ30 -> 0 | BM30: =BC30+BI30+BJ30-BL30 -> 0 | BP30: 5 | BR30: =BH30+BP30-BQ30 -> 40 | BS30: 200 | BT30: 10 | BU30: =BS30+BT30 -> 210 | BW30: =BM30+BS30+BT30-BV30 -> 210 | BZ30: 5 | CB30: =BR30+BZ30-CA30 -> 45 | CE30: =CC30+CD30 -> 0 | CF30: 210 | CG30: =BW30+CC30+CD30-CF30 -> 0 | CJ30: 5 | CL30: =CB30+CJ30-CK30 -> 50 | CO30: =CM30+CN30 -> 0 | CQ30: =CG30+CM30+CN30-CP30 -> 0 | CT30: 5 | CV30: =CL30+CT30-CU30 -> 55 | CY30: =CW30+CX30 -> 0 | DA30: =CQ30+CW30+CX30-CZ30 -> 0 | DD30: 5 | DF30: =CV30+DD30-DE30 -> 60 | DI30: =DG30+DH30 -> 0 | DK30: =DA30+DG30+DH30-DJ30 -> 0 | DN30: 10 | DP30: =DF30+DN30-DO30 -> 70 | DS30: =DQ30+DR30 -> 0 | DU30: =DK30+DQ30+DR30-DT30 -> 0 | DZ30: =DP30+DX30-DY30 -> 70 | EC30: =EA30+EB30 -> 0 | EE30: =DU30+EA30+EB30-ED30 -> 0 | EJ30: =DZ30+EH30-EI30 -> 70 | EM30: =EK30+EL30 -> 0 | EO30: =EE30+EK30+EL30-EN30 -> 0 | ET30: =EJ30+ER30-ES30 -> 70 | EW30: =EU30+EV30 -> 0 | EY30: =EO30+EU30+EV30-EX30 -> 0 | FD30: =ET30+FB30-FC30 -> 70 | FG30: =FE30+FF30 -> 0 | FI30: =EY30+FE30+FF30-FH30 -> 0 | FN30: =FD30+FL30-FM30 -> 70 | FQ30: =FO30+FP30 -> 0 | FS30: =FI30+FO30+FP30-FR30 -> 0 | FX30: 5 | FZ30: =DF30+FX30-FY30 -> 65 | GC30: =GA30+GB30 -> 0 | GE30: =DK30+GC30-GD30 -> 0 | GH30: 5 | GJ30: =+FZ30+GH30-GI30 -> 70 | GM30: =GK30+GL30 -> 0 | GO30: =+GE30+GM30-GN30 -> 0 | GT30: =GJ30+GR30-GS30 -> 70 | GW30: =GU30+GV30 -> 0 | GY30: =+GO30+GW30-GX30 -> 0
A31: 25 | B31: 21 | C31: 21 | D31: PRUNA SINCHIGUANOHEIDY NAOMI | E31: 0 | F31: 10 | H31: =E31+F31-G31 -> 10 | M31: =+I31+J31-L31 -> 0 | Q31: 5 | S31: =H31+Q31-R31 -> 15 | V31: =T31+U31 -> 0 | X31: =M31+T31+U31-W31 -> 0 | AB31: 5 | AD31: =S31+AB31-AC31 -> 20 | AG31: =AE31+AF31 -> 0 | AI31: =X31+AE31+AF31-AH31 -> 0 | AL31: 5 | AN31: =AD31+AL31-AM31 -> 25 | AQ31: =AO31+AP31 -> 0 | AS31: =AI31+AO31+AP31-AR31 -> 0 | AV31: 5 | AX31: =AN31+AV31-AW31 -> 30 | BA31: =AY31+AZ31 -> 0 | BC31: =AS31+AY31+AZ31-BB31 -> 0 | BF31: 5 | BH31: =AX31+BF31-BG31 -> 35 | BK31: =BI31+BJ31 -> 0 | BM31: =BC31+BI31+BJ31-BL31 -> 0 | BP31: 5 | BR31: =BH31+BP31-BQ31 -> 40 | BU31: =BS31+BT31 -> 0 | BW31: =BM31+BS31+BT31-BV31 -> 0 | BZ31: 5 | CB31: =BR31+BZ31-CA31 -> 45 | CE31: =CC31+CD31 -> 0 | CG31: =BW31+CC31+CD31-CF31 -> 0 | CJ31: 5 | CL31: =CB31+CJ31-CK31 -> 50 | CM31: 100 | CN31: 15 | CO31: =CM31+CN31 -> 115 | CQ31: =CG31+CM31+CN31-CP31 -> 115 | CT31: 5 | CV31: =CL31+CT31-CU31 -> 55 | CY31: =CW31+CX31 -> 0 | CZ31: 5 | DA31: =CQ31+CW31+CX31-CZ31 -> 110 | DD31: 5 | DF31: =CV31+DD31-DE31 -> 60 | DI31: =DG31+DH31 -> 0 | DJ31: 5 | DK31: =DA31+DG31+DH31-DJ31 -> 105 | DN31: 30 | DP31: =DF31+DN31-DO31 -> 90 | DS31: =DQ31+DR31 -> 0 | DU31: =DK31+DQ31+DR31-DT31 -> 105 | DZ31: =DP31+DX31-DY31 -> 90 | EC31: =EA31+EB31 -> 0 | EE31: =DU31+EA31+EB31-ED31 -> 105 | EJ31: =DZ31+EH31-EI31 -> 90 | EM31: =EK31+EL31 -> 0 | EO31: =EE31+EK31+EL31-EN31 -> 105 | ET31: =EJ31+ER31-ES31 -> 90 | EW31: =EU31+EV31 -> 0 | EY31: =EO31+EU31+EV31-EX31 -> 105 | FD31: =ET31+FB31-FC31 -> 90 | FG31: =FE31+FF31 -> 0 | FI31: =EY31+FE31+FF31-FH31 -> 105 | FN31: =FD31+FL31-FM31 -> 90 | FQ31: =FO31+FP31 -> 0 | FS31: =FI31+FO31+FP31-FR31 -> 105 | FX31: 5 | FZ31: =DF31+FX31-FY31 -> 65 | GC31: =GA31+GB31 -> 0 | GD31: 105 | GE31: =DK31+GC31-GD31 -> 0 | GH31: 5 | GJ31: =+FZ31+GH31-GI31 -> 70 | GM31: =GK31+GL31 -> 0 | GO31: =+GE31+GM31-GN31 -> 0 | GT31: =GJ31+GR31-GS31 -> 70 | GW31: =GU31+GV31 -> 0 | GY31: =+GO31+GW31-GX31 -> 0
A32: 26 | B32: 22 | C32: 22 | D32: PRUNA CANDO NORMA NATALY | E32: 0 | F32: 10 | H32: =E32+F32-G32 -> 10 | M32: =+I32+J32-L32 -> 0 | Q32: 5 | S32: =H32+Q32-R32 -> 15 | V32: =T32+U32 -> 0 | X32: =M32+T32+U32-W32 -> 0 | AB32: 5 | AD32: =S32+AB32-AC32 -> 20 | AE32: 100 | AF32: 15 | AG32: =AE32+AF32 -> 115 | AI32: =X32+AE32+AF32-AH32 -> 115 | AL32: 5 | AN32: =AD32+AL32-AM32 -> 25 | AQ32: =AO32+AP32 -> 0 | AR32: 5 | AS32: =AI32+AO32+AP32-AR32 -> 110 | AV32: 5 | AX32: =AN32+AV32-AW32 -> 30 | BA32: =AY32+AZ32 -> 0 | BB32: 5 | BC32: =AS32+AY32+AZ32-BB32 -> 105 | BF32: 5 | BH32: =AX32+BF32-BG32 -> 35 | BI32: 100 | BJ32: 15 | BK32: =BI32+BJ32 -> 115 | BL32: 105 | BM32: =BC32+BI32+BJ32-BL32 -> 115 | BP32: 5 | BR32: =BH32+BP32-BQ32 -> 40 | BU32: =BS32+BT32 -> 0 | BV32: 5 | BW32: =BM32+BS32+BT32-BV32 -> 110 | BZ32: 5 | CB32: =BR32+BZ32-CA32 -> 45 | CE32: =CC32+CD32 -> 0 | CF32: 5 | CG32: =BW32+CC32+CD32-CF32 -> 105 | CJ32: 5 | CL32: =CB32+CJ32-CK32 -> 50 | CM32: 100 | CN32: 15 | CO32: =CM32+CN32 -> 115 | CP32: 105 | CQ32: =CG32+CM32+CN32-CP32 -> 115 | CT32: 5 | CV32: =CL32+CT32-CU32 -> 55 | CY32: =CW32+CX32 -> 0 | CZ32: 5 | DA32: =CQ32+CW32+CX32-CZ32 -> 110 | DD32: 5 | DF32: =CV32+DD32-DE32 -> 60 | DI32: =DG32+DH32 -> 0 | DJ32: 105 | DK32: =DA32+DG32+DH32-DJ32 -> 5 | DN32: 5 | DP32: =DF32+DN32-DO32 -> 65 | DS32: =DQ32+DR32 -> 0 | DU32: =DK32+DQ32+DR32-DT32 -> 5 | DZ32: =DP32+DX32-DY32 -> 65 | EC32: =EA32+EB32 -> 0 | EE32: =DU32+EA32+EB32-ED32 -> 5 | EJ32: =DZ32+EH32-EI32 -> 65 | EM32: =EK32+EL32 -> 0 | EO32: =EE32+EK32+EL32-EN32 -> 5 | ET32: =EJ32+ER32-ES32 -> 65 | EW32: =EU32+EV32 -> 0 | EY32: =EO32+EU32+EV32-EX32 -> 5 | FD32: =ET32+FB32-FC32 -> 65 | FG32: =FE32+FF32 -> 0 | FI32: =EY32+FE32+FF32-FH32 -> 5 | FN32: =FD32+FL32-FM32 -> 65 | FQ32: =FO32+FP32 -> 0 | FS32: =FI32+FO32+FP32-FR32 -> 5 | FX32: 5 | FZ32: =DF32+FX32-FY32 -> 65 | GC32: =GA32+GB32 -> 0 | GE32: =DK32+GC32-GD32 -> 5 | GH32: 5 | GJ32: =+FZ32+GH32-GI32 -> 70 | GM32: =GK32+GL32 -> 0 | GO32: =+GE32+GM32-GN32 -> 5 | GT32: =GJ32+GR32-GS32 -> 70 | GW32: =GU32+GV32 -> 0 | GY32: =+GO32+GW32-GX32 -> 5
A33: 27 | B33: 23 | C33: 23 | D33: RODRIGUEZ HERRERA MIRIAM ELIZABETH | F33: 10 | H33: =E33+F33-G33 -> 10 | M33: =+I33+J33-L33 -> 0 | Q33: 5 | S33: =H33+Q33-R33 -> 15 | V33: =T33+U33 -> 0 | X33: =M33+T33+U33-W33 -> 0 | AB33: 5 | AD33: =S33+AB33-AC33 -> 20 | AG33: =AE33+AF33 -> 0 | AI33: =X33+AE33+AF33-AH33 -> 0 | AL33: 5 | AN33: =AD33+AL33-AM33 -> 25 | AQ33: =AO33+AP33 -> 0 | AS33: =AI33+AO33+AP33-AR33 -> 0 | AV33: 5 | AX33: =AN33+AV33-AW33 -> 30 | BA33: =AY33+AZ33 -> 0 | BC33: =AS33+AY33+AZ33-BB33 -> 0 | BF33: 5 | BH33: =AX33+BF33-BG33 -> 35 | BK33: =BI33+BJ33 -> 0 | BM33: =BC33+BI33+BJ33-BL33 -> 0 | BP33: 5 | BR33: =BH33+BP33-BQ33 -> 40 | BU33: =BS33+BT33 -> 0 | BW33: =BM33+BS33+BT33-BV33 -> 0 | BZ33: 5 | CB33: =BR33+BZ33-CA33 -> 45 | CE33: =CC33+CD33 -> 0 | CG33: =BW33+CC33+CD33-CF33 -> 0 | CJ33: 5 | CL33: =CB33+CJ33-CK33 -> 50 | CO33: =CM33+CN33 -> 0 | CQ33: =CG33+CM33+CN33-CP33 -> 0 | CT33: 5 | CV33: =CL33+CT33-CU33 -> 55 | CW33: 100 | CX33: 15 | CY33: =CW33+CX33 -> 115 | DA33: =CQ33+CW33+CX33-CZ33 -> 115 | DD33: 5 | DF33: =CV33+DD33-DE33 -> 60 | DI33: =DG33+DH33 -> 0 | DJ33: 5 | DK33: =DA33+DG33+DH33-DJ33 -> 110 | DN33: 20 | DP33: =DF33+DN33-DO33 -> 80 | DS33: =DQ33+DR33 -> 0 | DU33: =DK33+DQ33+DR33-DT33 -> 110 | DZ33: =DP33+DX33-DY33 -> 80 | EC33: =EA33+EB33 -> 0 | EE33: =DU33+EA33+EB33-ED33 -> 110 | EJ33: =DZ33+EH33-EI33 -> 80 | EM33: =EK33+EL33 -> 0 | EO33: =EE33+EK33+EL33-EN33 -> 110 | ET33: =EJ33+ER33-ES33 -> 80 | EW33: =EU33+EV33 -> 0 | EY33: =EO33+EU33+EV33-EX33 -> 110 | FD33: =ET33+FB33-FC33 -> 80 | FG33: =FE33+FF33 -> 0 | FI33: =EY33+FE33+FF33-FH33 -> 110 | FN33: =FD33+FL33-FM33 -> 80 | FQ33: =FO33+FP33 -> 0 | FS33: =FI33+FO33+FP33-FR33 -> 110 | FX33: 5 | FZ33: =DF33+FX33-FY33 -> 65 | GC33: =GA33+GB33 -> 0 | GD33: 5 | GE33: =DK33+GC33-GD33 -> 105 | GH33: 5 | GJ33: =+FZ33+GH33-GI33 -> 70 | GK33: 100 | GL33: 15 | GM33: =GK33+GL33 -> 115 | GN33: 105 | GO33: =+GE33+GM33-GN33 -> 115 | GT33: =GJ33+GR33-GS33 -> 70 | GW33: =GU33+GV33 -> 0 | GY33: =+GO33+GW33-GX33 -> 115
A34: 29 | B34: 24 | C34: 24 | D34: SINCHIGUANO BASANTES VERÓNICAGISSELA | E34: 0 | F34: 10 | H34: =E34+F34-G34 -> 10 | I34: 100 | J34: 15 | K34: =+I34+J34 -> 115 | M34: =+I34+J34-L34 -> 115 | Q34: 5 | S34: =H34+Q34-R34 -> 15 | V34: =T34+U34 -> 0 | W34: 5 | X34: =M34+T34+U34-W34 -> 110 | AB34: 5 | AD34: =S34+AB34-AC34 -> 20 | AG34: =AE34+AF34 -> 0 | AH34: 5 | AI34: =X34+AE34+AF34-AH34 -> 105 | AL34: 5 | AN34: =AD34+AL34-AM34 -> 25 | AO34: 100 | AP34: 15 | AQ34: =AO34+AP34 -> 115 | AR34: 105 | AS34: =AI34+AO34+AP34-AR34 -> 115 | AV34: 5 | AX34: =AN34+AV34-AW34 -> 30 | BA34: =AY34+AZ34 -> 0 | BB34: 5 | BC34: =AS34+AY34+AZ34-BB34 -> 110 | BF34: 5 | BH34: =AX34+BF34-BG34 -> 35 | BK34: =BI34+BJ34 -> 0 | BL34: 5 | BM34: =BC34+BI34+BJ34-BL34 -> 105 | BP34: 5 | BR34: =BH34+BP34-BQ34 -> 40 | BU34: =BS34+BT34 -> 0 | BV34: 105 | BW34: =BM34+BS34+BT34-BV34 -> 0 | BZ34: 5 | CB34: =BR34+BZ34-CA34 -> 45 | CE34: =CC34+CD34 -> 0 | CG34: =BW34+CC34+CD34-CF34 -> 0 | CJ34: 5 | CL34: =CB34+CJ34-CK34 -> 50 | CO34: =CM34+CN34 -> 0 | CQ34: =CG34+CM34+CN34-CP34 -> 0 | CT34: 5 | CV34: =CL34+CT34-CU34 -> 55 | CY34: =CW34+CX34 -> 0 | DA34: =CQ34+CW34+CX34-CZ34 -> 0 | DD34: 5 | DF34: =CV34+DD34-DE34 -> 60 | DI34: =DG34+DH34 -> 0 | DK34: =DA34+DG34+DH34-DJ34 -> 0 | DN34: 40 | DP34: =DF34+DN34-DO34 -> 100 | DS34: =DQ34+DR34 -> 0 | DU34: =DK34+DQ34+DR34-DT34 -> 0 | DZ34: =DP34+DX34-DY34 -> 100 | EC34: =EA34+EB34 -> 0 | EE34: =DU34+EA34+EB34-ED34 -> 0 | EJ34: =DZ34+EH34-EI34 -> 100 | EM34: =EK34+EL34 -> 0 | EO34: =EE34+EK34+EL34-EN34 -> 0 | ET34: =EJ34+ER34-ES34 -> 100 | EW34: =EU34+EV34 -> 0 | EY34: =EO34+EU34+EV34-EX34 -> 0 | FD34: =ET34+FB34-FC34 -> 100 | FG34: =FE34+FF34 -> 0 | FI34: =EY34+FE34+FF34-FH34 -> 0 | FN34: =FD34+FL34-FM34 -> 100 | FQ34: =FO34+FP34 -> 0 | FS34: =FI34+FO34+FP34-FR34 -> 0 | FX34: 5 | FZ34: =DF34+FX34-FY34 -> 65 | GC34: =GA34+GB34 -> 0 | GE34: =DK34+GC34-GD34 -> 0 | GH34: 5 | GJ34: =+FZ34+GH34-GI34 -> 70 | GM34: =GK34+GL34 -> 0 | GO34: =+GE34+GM34-GN34 -> 0 | GT34: =GJ34+GR34-GS34 -> 70 | GW34: =GU34+GV34 -> 0 | GY34: =+GO34+GW34-GX34 -> 0
A35: 30 | B35: 25 | C35: 25 | D35: ZAPATA HERRERA ALEX DAVID | E35: 0 | F35: 10 | H35: =E35+F35-G35 -> 10 | Q35: 5 | S35: =H35+Q35-R35 -> 15 | V35: =T35+U35 -> 0 | X35: =M35+T35+U35-W35 -> 0 | AB35: 5 | AD35: =S35+AB35-AC35 -> 20 | AG35: =AE35+AF35 -> 0 | AI35: =X35+AE35+AF35-AH35 -> 0 | AL35: 5 | AN35: =AD35+AL35-AM35 -> 25 | AQ35: =AO35+AP35 -> 0 | AS35: =AI35+AO35+AP35-AR35 -> 0 | AV35: 5 | AX35: =AN35+AV35-AW35 -> 30 | BA35: =AY35+AZ35 -> 0 | BC35: =AS35+AY35+AZ35-BB35 -> 0 | BF35: 5 | BH35: =AX35+BF35-BG35 -> 35 | BK35: =BI35+BJ35 -> 0 | BM35: =BC35+BI35+BJ35-BL35 -> 0 | BP35: 5 | BR35: =BH35+BP35-BQ35 -> 40 | BS35: 200 | BT35: 30 | BU35: =BS35+BT35 -> 230 | BW35: =BM35+BS35+BT35-BV35 -> 230 | BZ35: 5 | CB35: =BR35+BZ35-CA35 -> 45 | CE35: =CC35+CD35 -> 0 | CF35: 10 | CG35: =BW35+CC35+CD35-CF35 -> 220 | CJ35: 5 | CL35: =CB35+CJ35-CK35 -> 50 | CO35: =CM35+CN35 -> 0 | CP35: 10 | CQ35: =CG35+CM35+CN35-CP35 -> 210 | CT35: 5 | CV35: =CL35+CT35-CU35 -> 55 | CW35: 200 | CX35: 30 | CY35: =CW35+CX35 -> 230 | CZ35: 210 | DA35: =CQ35+CW35+CX35-CZ35 -> 230 | DD35: 5 | DF35: =CV35+DD35-DE35 -> 60 | DI35: =DG35+DH35 -> 0 | DJ35: 10 | DK35: =DA35+DG35+DH35-DJ35 -> 220 | DN35: 10 | DP35: =DF35+DN35-DO35 -> 70 | DQ35: 400 | DR35: 72 | DS35: =DQ35+DR35 -> 472 | DU35: =DK35+DQ35+DR35-DT35 -> 692 | DZ35: =DP35+DX35-DY35 -> 70 | EC35: =EA35+EB35 -> 0 | EE35: =DU35+EA35+EB35-ED35 -> 692 | EJ35: =DZ35+EH35-EI35 -> 70 | EM35: =EK35+EL35 -> 0 | EO35: =EE35+EK35+EL35-EN35 -> 692 | ET35: =EJ35+ER35-ES35 -> 70 | EW35: =EU35+EV35 -> 0 | EY35: =EO35+EU35+EV35-EX35 -> 692 | FD35: =ET35+FB35-FC35 -> 70 | FG35: =FE35+FF35 -> 0 | FI35: =EY35+FE35+FF35-FH35 -> 692 | FN35: =FD35+FL35-FM35 -> 70 | FQ35: =FO35+FP35 -> 0 | FS35: =FI35+FO35+FP35-FR35 -> 692 | FX35: 5 | FZ35: =DF35+FX35-FY35 -> 65 | GC35: =GA35+GB35 -> 0 | GD35: 10 | GE35: =DK35+GC35-GD35 -> 210 | GH35: 5 | GJ35: =+FZ35+GH35-GI35 -> 70 | GK35: 200 | GL35: 30 | GM35: =GK35+GL35 -> 230 | GN35: 210 | GO35: =+GE35+GM35-GN35 -> 230 | GT35: =GJ35+GR35-GS35 -> 70 | GW35: =GU35+GV35 -> 0 | GY35: =+GO35+GW35-GX35 -> 230
E36: =SUM(E11:E35) -> 0 | F36: =SUM(F11:F35) -> 250 | H36: =SUM(H11:H35) -> 250 | I36: =SUM(I11:I35) -> 100 | J36: =SUM(J11:J35) -> 15 | K36: =SUM(K11:K35) -> 115 | L36: =SUM(L11:L35) -> 0 | M36: =SUM(M11:M35) -> 115 | N36: =SUM(N11:N35) -> 0 | Q36: =SUM(Q11:Q35) -> 105 | R36: =SUM(R11:R35) -> 0 | S36: =SUM(S11:S35) -> 355 | T36: =SUM(T11:T35) -> 200 | U36: =SUM(U11:U35) -> 30 | V36: =SUM(V11:V35) -> 230 | W36: =SUM(W11:W35) -> 5 | X36: =SUM(X11:X35) -> 340 | Z36: =SUM(Z11:Z35) -> 0 | AB36: =SUM(AB11:AB35) -> 125 | AC36: =SUM(AC11:AC35) -> 0 | AD36: =SUM(AD11:AD35) -> 480 | AE36: =SUM(AE11:AE35) -> 200 | AF36: =SUM(AF11:AF35) -> 30 | AG36: =SUM(AG11:AG35) -> 230 | AH36: =SUM(AH11:AH35) -> 15 | AI36: =SUM(AI11:AI35) -> 555 | AJ36: =SUM(AJ11:AJ35) -> 0 | AL36: =SUM(AL11:AL35) -> 145 | AM36: =SUM(AM11:AM35) -> 0 | AN36: =SUM(AN11:AN35) -> 625 | AO36: =SUM(AO11:AO35) -> 300 | AP36: =SUM(AP11:AP35) -> 45 | AQ36: =SUM(AQ11:AQ35) -> 345 | AR36: =SUM(AR11:AR35) -> 125 | AS36: =SUM(AS11:AS35) -> 775 | AT36: =SUM(AT11:AT35) -> 0 | AV36: =SUM(AV11:AV35) -> 125 | AW36: =SUM(AW11:AW35) -> 0 | AX36: =SUM(AX11:AX35) -> 750 | AY36: =SUM(AY11:AY35) -> 380 | AZ36: =SUM(AZ11:AZ35) -> 57 | BA36: =SUM(BA11:BA35) -> 437 | BB36: =SUM(BB11:BB35) -> 235 | BC36: =SUM(BC11:BC35) -> 977 | BD36: =SUM(BD11:BD35) -> 0 | BF36: =SUM(BF11:BF35) -> 125 | BG36: =SUM(BG11:BG35) -> 0 | BH36: =SUM(BH11:BH35) -> 875 | BI36: =SUM(BI11:BI35) -> 380 | BJ36: =SUM(BJ11:BJ35) -> 57 | BK36: =SUM(BK11:BK35) -> 437 | BL36: =SUM(BL11:BL35) -> 244 | BM36: =SUM(BM11:BM35) -> 1170 | BN36: =SUM(BN11:BN35) -> 0 | BP36: =SUM(BP11:BP35) -> 125 | BQ36: =SUM(BQ11:BQ35) -> 0 | BR36: =SUM(BR11:BR35) -> 1000 | BS36: =SUM(BS11:BS35) -> 400 | BT36: =SUM(BT11:BT35) -> 40 | BU36: =SUM(BU11:BU35) -> 440 | BV36: =SUM(BV11:BV35) -> 353 | BW36: =SUM(BW11:BW35) -> 1257 | BX36: =SUM(BX11:BX35) -> 0 | BZ36: =SUM(BZ11:BZ35) -> 125 | CA36: =SUM(CA11:CA35) -> 0 | CB36: =SUM(CB11:CB35) -> 1125 | CC36: =SUM(CC11:CC35) -> 800 | CD36: =SUM(CD11:CD35) -> 120 | CE36: =SUM(CE11:CE35) -> 920 | CF36: =SUM(CF11:CF35) -> 638 | CG36: =SUM(CG11:CG35) -> 1539 | CH36: =SUM(CH11:CH35) -> 0 | CJ36: =SUM(CJ11:CJ35) -> 125 | CK36: =SUM(CK11:CK35) -> 0 | CL36: =SUM(CL11:CL35) -> 1250 | CM36: =SUM(CM11:CM35) -> 600 | CN36: =SUM(CN11:CN35) -> 90 | CO36: =SUM(CO11:CO35) -> 690 | CP36: =SUM(CP11:CP35) -> 449 | CQ36: =SUM(CQ11:CQ35) -> 1780 | CR36: =SUM(CR11:CR35) -> 0 | CT36: =SUM(CT11:CT35) -> 125 | CU36: =SUM(CU11:CU35) -> 0 | CV36: =SUM(CV11:CV35) -> 1375 | CW36: =SUM(CW11:CW35) -> 400 | CY36: =SUM(CY11:CY35) -> 460 | CZ36: =SUM(CZ11:CZ35) -> 280 | DA36: =SUM(DA11:DA35) -> 1960 | DB36: =SUM(DB11:DB35) -> 0 | DD36: =SUM(DD11:DD35) -> 125 | DE36: =SUM(DE11:DE35) -> 0 | DF36: =SUM(DF11:DF35) -> 1500 | DG36: =SUM(DG11:DG35) -> 1100 | DH36: =SUM(DH11:DH35) -> 165 | DI36: =SUM(DI11:DI35) -> 1265 | DJ36: =SUM(DJ11:DJ35) -> 990 | DK36: =SUM(DK11:DK35) -> 2235 | DL36: =SUM(DL11:DL35) -> 0 | DN36: =SUM(DN11:DN35) -> 351.78 | DO36: =SUM(DO11:DO35) -> 0 | DP36: =SUM(DP11:DP35) -> 1851.78 | DQ36: =SUM(DQ11:DQ35) -> 1300 | DR36: =SUM(DR11:DR35) -> 234 | DS36: =SUM(DS11:DS35) -> 1534 | DT36: =SUM(DT11:DT35) -> 796.72 | DU36: =SUM(DU11:DU35) -> 2972.28 | DV36: 10 | DX36: =SUM(DX11:DX35) -> 0 | DY36: =SUM(DY11:DY35) -> 0 | DZ36: =SUM(DZ11:DZ35) -> 1851.78 | EA36: =SUM(EA11:EA35) -> 0 | EB36: =SUM(EB11:EB35) -> 0 | EC36: =SUM(EC11:EC35) -> 0 | ED36: =SUM(ED11:ED35) -> 0 | EE36: =SUM(EE11:EE35) -> 2972.28 | EF36: =SUM(EF11:EF35) -> 0 | EH36: =SUM(EH11:EH35) -> 0 | EI36: =SUM(EI11:EI35) -> 0 | EJ36: =SUM(EJ11:EJ35) -> 1851.78 | EK36: =SUM(EK11:EK35) -> 0 | EL36: =SUM(EL11:EL35) -> 0 | EM36: =SUM(EM11:EM35) -> 0 | EN36: =SUM(EN11:EN35) -> 0 | EO36: =SUM(EO11:EO35) -> 2972.28 | EP36: =SUM(EP11:EP35) -> 0 | ER36: =SUM(ER11:ER35) -> 0 | ES36: =SUM(ES11:ES35) -> 0 | ET36: =SUM(ET11:ET35) -> 1851.78 | EU36: =SUM(EU11:EU35) -> 0 | EV36: =SUM(EV11:EV35) -> 0 | EW36: =SUM(EW11:EW35) -> 0 | EX36: =SUM(EX11:EX35) -> 0 | EY36: =SUM(EY11:EY35) -> 2972.28 | EZ36: =SUM(EZ11:EZ35) -> 0 | FB36: =SUM(FB11:FB35) -> 0 | FC36: =SUM(FC11:FC35) -> 0 | FD36: =SUM(FD11:FD35) -> 1851.78 | FE36: =SUM(FE11:FE35) -> 0 | FF36: =SUM(FF11:FF35) -> 0 | FG36: =SUM(FG11:FG35) -> 0 | FH36: =SUM(FH11:FH35) -> 0 | FI36: =SUM(FI11:FI35) -> 2972.28 | FJ36: =SUM(FJ11:FJ35) -> 0 | FL36: =SUM(FL11:FL35) -> 0 | FM36: =SUM(FM11:FM35) -> 0 | FN36: =SUM(FN11:FN35) -> 1851.78 | FO36: =SUM(FO11:FO35) -> 0 | FP36: =SUM(FP11:FP35) -> 0 | FQ36: =SUM(FQ11:FQ35) -> 0 | FR36: =SUM(FR11:FR35) -> 0 | FS36: =SUM(FS11:FS35) -> 2972.28 | FT36: =SUM(FT11:FT35) -> 0 | FX36: =SUM(FX11:FX35) -> 125 | FY36: =SUM(FY11:FY35) -> 0 | FZ36: =SUM(FZ11:FZ35) -> 1625 | GA36: =SUM(GA11:GA35) -> 700 | GB36: =SUM(GB11:GB35) -> 105 | GC36: =SUM(GC11:GC35) -> 805 | GD36: =SUM(GD11:GD35) -> 600 | GE36: =SUM(GE11:GE35) -> 2440 | GF36: =SUM(GF11:GF35) -> 0 | GH36: =SUM(GH11:GH35) -> 125 | GI36: =SUM(GI11:GI35) -> 0 | GJ36: =SUM(GJ11:GJ35) -> 1750 | GK36: =SUM(GK11:GK35) -> 635 | GL36: =SUM(GL11:GL35) -> 95.25 | GM36: =SUM(GM11:GM35) -> 730.25 | GN36: =SUM(GN11:GN35) -> 420 | GO36: =SUM(GO11:GO35) -> 2750.25 | GP36: =SUM(GP11:GP35) -> 0 | GR36: =SUM(GR11:GR35) -> 0 | GS36: =SUM(GS11:GS35) -> 0 | GT36: =SUM(GT11:GT35) -> 1750 | GU36: =SUM(GU11:GU35) -> 0 | GV36: =SUM(GV11:GV35) -> 0 | GW36: =SUM(GW11:GW35) -> 0 | GX36: =SUM(GX11:GX35) -> 0 | GY36: =SUM(GY11:GY35) -> 2750.25 | GZ36: =SUM(GZ11:GZ35) -> 0
F37: =F36 -> 250 | H37: =H36 -> 250 | I37: =I36 -> 100 | J37: =J36 -> 15 | K37: =K36 -> 115 | L37: =L36 -> 0 | N37: =N36 -> 0 | Q37: =Q36+F37 -> 355 | R37: =R36+G37 -> 0 | T37: =T36+I37 -> 300 | U37: =U36+J37 -> 45 | W37: =W36+L37 -> 5 | Z37: =Z36+N37 -> 0 | AB37: =AB36+Q37 -> 480 | AC37: =AC36+R37 -> 0 | AE37: =AE36+T37 -> 500 | AF37: =AF36+U37 -> 75 | AH37: =AH36+W37 -> 20 | AJ37: =AJ36+Z37 -> 0 | AL37: =AL36+AB37 -> 625 | AM37: =AM36+AC37 -> 0 | AO37: =AO36+AE37 -> 800 | AP37: =AP36+AF37 -> 120 | AR37: =AR36+AH37 -> 145 | AT37: =AT36+AM37 -> 0 | AV37: =AV36+AL37 -> 750 | AW37: =AW36+AM37 -> 0 | AY37: =AY36+AO37 -> 1180 | AZ37: =AZ36+AP37 -> 177 | BB37: =BB36+AR37 -> 380 | BD37: =BD36+AT37 -> 0 | BF37: =BF36+AV37 -> 875 | BG37: =BG36+AW37 -> 0 | BI37: =BI36+AY37 -> 1560 | BJ37: =BJ36+AZ37 -> 234 | BL37: =BL36+BB37 -> 624 | BN37: =BN36+BD37 -> 0 | BP37: =BP36+BF37 -> 1000 | BQ37: =BQ36+BG37 -> 0 | BS37: =BS36+BI37 -> 1960 | BT37: =BT36+BJ37 -> 274 | BV37: =BV36+BL37 -> 977 | BX37: =BX36+BN37 -> 0 | BZ37: =BZ36+BP37 -> 1125 | CA37: =CA36+BQ37 -> 0 | CC37: =CC36+BS37 -> 2760 | CD37: =CD36+BT37 -> 394 | CF37: =CF36+BV37 -> 1615 | CH37: =CH36+BX37 -> 0 | CJ37: =CJ36+BZ37 -> 1250 | CK37: =CK36+CA37 -> 0 | CM37: =CM36+CC37 -> 3360 | CN37: =CN36+CD37 -> 484 | CP37: =CP36+CF37 -> 2064 | CR37: =CR36+CH37 -> 0 | CT37: =CT36+CJ37 -> 1375 | CU37: =CU36+CK37 -> 0 | CW37: =CW36+CM37 -> 3760 | CX37: =CX36+CN37 -> 484 | CZ37: =CZ36+CP37 -> 2344 | DB37: =DB36+CR37 -> 0 | DD37: =DD36+CT37 -> 1500 | DE37: =DE36+CU37 -> 0 | DG37: =DG36+CW37 -> 4860 | DH37: =DH36+CX37 -> 649 | DJ37: =DJ36+CZ37 -> 3334 | DL37: =DL36+DB37 -> 0 | DN37: =DN36+DF36-DO36 -> 1851.78 | DO37: =DO36+DE37 -> 0 | DQ37: =DQ36+DG37 -> 6160 | DR37: =DR36+DH37 -> 883 | DT37: =DT36+DJ37 -> 4130.72 | DV37: =DV36+DL37 -> 10 | DX37: =DX36+DP36-DY36 -> 1851.78 | DY37: =DY36+DO37 -> 0 | EA37: =EA36+DQ37 -> 6160 | EB37: =EB36+DR37 -> 883 | ED37: =ED36+DT37 -> 4130.72 | EF37: =EF36+DV37 -> 10 | EH37: =EH36+DZ36-EI36 -> 1851.78 | EI37: =EI36+DY37 -> 0 | EK37: =EK36+EA37 -> 6160 | EL37: =EL36+EB37 -> 883 | EN37: =EN36+ED37 -> 4130.72 | EP37: =EP36+EF37 -> 10 | ER37: =ER36+EJ36-ES36 -> 1851.78 | ES37: =ES36+EI37 -> 0 | EU37: =EU36+EK37 -> 6160 | EV37: =EV36+EL37 -> 883 | EX37: =EX36+EN37 -> 4130.72 | EZ37: =EZ36+EP37 -> 10 | FB37: =FB36+ET36-FC36 -> 1851.78 | FC37: =FC36+ES37 -> 0 | FE37: =FE36+EU37 -> 6160 | FF37: =FF36+EV37 -> 883 | FH37: =FH36+EX37 -> 4130.72 | FJ37: =FJ36+EZ37 -> 10 | FL37: =FL36+FD36-FM36 -> 1851.78 | FM37: =FM36+FC37 -> 0 | FO37: =FO36+FE37 -> 6160 | FP37: =FP36+FF37 -> 883 | FR37: =FR36+FH37 -> 4130.72 | FT37: =FT36+FJ37 -> 10 | FX37: =FX36+FN37 -> 125 | FY37: =FY36+FO37 -> 6160 | GA37: =GA36+FQ37 -> 700 | GB37: =GB36+FR37 -> 4235.72 | GD37: =GD36+FT37 -> 610 | GF37: =GF36+FV37 -> 0 | GH37: =GH36+FX37 -> 250 | GI37: =GI36+FY37 -> 6160 | GK37: =GK36+GA37 -> 1335 | GL37: =GL36+GB37 -> 4330.97 | GN37: =GN36+GD37 -> 1030 | GP37: =GP36+GF37 -> 0 | GR37: =GR36+GH37 -> 250 | GS37: =GS36+GI37 -> 6160 | GU37: =GU36+GK37 -> 1335 | GV37: =GV36+GL37 -> 4330.97 | GX37: =GX36+GN37 -> 1030 | GZ37: =GZ36+GP37 -> 0
F39: Socios que ingresaron a la caja luego de ser conformada
F40: Nota. Se inicia actividades en la caja con un fondo común procedente de una rifa realizada por los socios fundadores

Sheet CAJA CHICA
B2: CAJA DE AHORRO
B4: COMUNAL
B5: VERDECOCHA
B6: Sembrando juntos para un futuro
B8: REUNION | C8: RESUMEN DE CAJA CHICA
C9: FECHA | D9: DESCRIPCIÓN | E9: INGRESOS | F9: EGRESOS | G9: SALDO
B11: 1 | C11: 45469 | D11: Aporte mìnimo mensual (0,50 por socio) | E11: =0.5*25 -> 12.5 | G11: =+E11-F11 -> 12.5
B12: 2 | C12: 45469 | D12: suministros de oficina | F12: 10.5 | G12: =+G11+E12-F12 -> 2
B13: 3 | C13: 45534 | D13: Aporte mìnimo mensual (0,50 por socio) | E13: =0.5*25 -> 12.5 | G13: =+G12+E13-F13 -> 14.5
B14: 4 | C14: 45534 | D14: Aporte Solidario | E14: 24 | G14: =+G13+E14-F14 -> 38.5
B15: 5 | C15: 45534 | D15: Colaboraciòn solodaria (Joana Herrera) | F15: 20 | G15: =+G14+E15-F15 -> 18.5
B16: 6 | C16: 45562 | D16: Aporte mìnimo mensual (0,50 por socio) | E16: =0.5*25 -> 12.5 | G16: =+G15+E16-F16 -> 31
B17: 7 | C17: 45589 | D17: Aporte mìnimo mensual (0,50 por socio) | E17: =0.5*25 -> 12.5 | G17: =+G16+E17-F17 -> 43.5
B18: 8 | C18: 45625 | D18: Aporte mìnimo mensual (0,50 por socio) | E18: =0.5*25 -> 12.5 | G18: =+G17+E18-F18 -> 56
B19: 9 | C19: 45625 | D19: Copias e impresiones | F19: 2.79 | G19: =+G18+E19-F19 -> 53.21
B20: 10 | C20: 45688 | D20: Aporte mìnimo mensual (0,50 por socio) | E20: =0.5*25 -> 12.5 | G20: =+G19+E20-F20 -> 65.71
B21: 11 | C21: 45688 | D21: Atrasos (4 personas) | E21: =1*4 -> 4 | G21: =+G20+E21-F21 -> 69.71
B22: 12 | C22: 45719 | D22: Aporte mìnimo mensual (0,50 por socio) | E22: =0.5*25 -> 12.5 | G22: =+G21+E22-F22 -> 82.21
B23: 13 | C23: 45747 | D23: Aporte mìnimo mensual (0,50 por socio) | E23: =0.5*25 -> 12.5 | G23: =+G22+E23-F23 -> 94.71
B24: 14 | C24: 45747 | D24: suministro de oficina (compra de marcadores y papelote) | F24: 2.4 | G24: =+G23+E24-F24 -> 92.31
B25: 15 | C25: 45771 | D25: Colaboraciòn solodaria (Rafael Molina) | F25: 20 | G25: =+G24+E25-F25 -> 72.31
B26: 16 | C26: 45779 | D26: Compra de Matriz Contable | F26: 60 | G26: =+G25+E26-F26 -> 12.31
B27: 17 | C27: 45779 | D27: Aporte mìnimo mensual (0,50 por socio) | E27: =0.5*25 -> 12.5 | G27: =+G26+E27-F27 -> 24.81
B28: 18 | C28: 45794 | D28: Gastos varios (Refrigerio) | F28: 10 | G28: =+G27+E28-F28 -> 14.81
B29: 19 | C29: 45807 | D29: Aporte mìnimo mensual (0,50 por socio) | E29: =0.5*25 -> 12.5 | G29: =+G28+E29-F29 -> 27.31
B30: 20 | C30: 45807 | D30: Multas (Juan David - Miriam) | E30: 10 | G30: =+G29+E30-F30 -> 37.31
B31: 21 | C31: 45589 | G31: =+G30+E31-F31 -> 37.31
B32: 22 | C32: 45589 | G32: =+G31+E32-F32 -> 37.31
B33: 23 | C33: 45589 | G33: =+G32+E33-F33 -> 37.31
B34: 24 | C34: 45589 | G34: =+G33+E34-F34 -> 37.31
B35: 25 | C35: 45589 | G35: =+G34+E35-F35 -> 37.31
B36: 26 | C36: 45589 | G36: =+G35+E36-F36 -> 37.31
B37: 27 | C37: 45589 | G37: =+G36+E37-F37 -> 37.31
B38: 28 | C38: 45589 | G38: =+G37+E38-F38 -> 37.31
B39: 29 | C39: 45589 | G39: =+G38+E39-F39 -> 37.31
B40: 30 | C40: 45589 | G40: =+G39+E40-F40 -> 37.31
B41: 31 | C41: 45589 | G41: =+G40+E41-F41 -> 37.31
B42: 32 | C42: 45589 | G42: =+G41+E42-F42 -> 37.31
... B521: 511 | C521: 45589 | G521: =+G520+E521-F521 -> 37.31

Sheet INTERÈSES 
B1: CAJA DE AHORRO
B3: COMUNAL
B4: VERDECOCHA
B5: Sembrando juntos para un futuro
A7: Nº | B7: SOCIO | C7: 2024 COBRADO | J7: TOTAL INTERÉSES POR SOCIO | L7: 2025 | X7: TOTAL INTERÉSES POR SOCIO | Z7: 2026 | AM7: 2027 | AZ7: 2028 | BM7: 2029
C8: JUNIO | D8: JULIO | E8: AGOSTO | F8: SEPTIEMBRE | G8: OCTUBRE | H8: NOVIEMBRE | I8: DICIEMBRE | L8: ENERO | M8: FEBRERO | N8: MARZO | O8: ABRIL | P8: MAYO | Q8: JUNIO | R8: JULIO | S8: AGOSTO | T8: SEPTIEMBRE | U8: OCTUBRE | V8: NOVIEMBRE | W8: DICIEMBRE | Z8: ENERO | AA8: FEBRERO | AB8: MARZO | AC8: ABRIL | AD8: MAYO | AE8: JUNIO | AF8: JULIO | AG8: AGOSTO | AH8: SEPTIEMBRE | AI8: OCTUBRE | AJ8: NOVIEMBRE | AK8: DICIEMBRE | AM8: ENERO | AN8: FEBRERO | AO8: MARZO | AP8: ABRIL | AQ8: MAYO | AR8: JUNIO | AS8: JULIO | AT8: AGOSTO | AU8: SEPTIEMBRE | AV8: OCTUBRE | AW8: NOVIEMBRE | AX8: DICIEMBRE | AZ8: ENERO | BA8: FEBRERO | BB8: MARZO | BC8: ABRIL | BD8: MAYO | BE8: JUNIO | BF8: JULIO | BG8: AGOSTO | BH8: SEPTIEMBRE | BI8: OCTUBRE | BJ8: NOVIEMBRE | BK8: DICIEMBRE | BM8: ENERO | BN8: FEBRERO | BO8: MARZO | BP8: ABRIL | BQ8: MAYO | BR8: JUNIO | BS8: JULIO | BT8: AGOSTO | BU8: SEPTIEMBRE | BV8: OCTUBRE | BW8: NOVIEMBRE | BX8: DICIEMBRE
A9: 1 | B9: ALVAREZ PRUNA LUIS HERIBERTO | J9: =SUM(C9:I9) -> 0 | O9: 5 | P9: 5 | Q9: 5 | X9: =SUM(L9:W9) -> 15 | AL9: =SUM(Z9:AK9) -> 0 | AY9: =SUM(AM9:AX9) -> 0 | BL9: =SUM(AZ9:BK9) -> 0 | BY9: =SUM(BM9:BX9) -> 0
A10: 2 | B10: CHACHAPOYA TOAPANTA RAUL GERARDO | J10: =SUM(C10:I10) -> 0 | R10: 5 | S10: 5 | T10: 5 | X10: =SUM(L10:W10) -> 15 | AL10: =SUM(Z10:AK10) -> 0 | AY10: =SUM(AM10:AX10) -> 0 | BL10: =SUM(AZ10:BK10) -> 0 | BY10: =SUM(BM10:BX10) -> 0
A11: 3 | B11: CHICAIZA CHACON GLORIA MARINA | J11: =SUM(C11:I11) -> 0 | M11: 10 | N11: 10 | O11: 10 | P11: 5 | Q11: 5 | R11: 5 | X11: =SUM(L11:W11) -> 45 | AL11: =SUM(Z11:AK11) -> 0 | AY11: =SUM(AM11:AX11) -> 0 | BL11: =SUM(AZ11:BK11) -> 0 | BY11: =SUM(BM11:BX11) -> 0
A12: 4 | B12: HERRERA ZAPATA CARMEN ALICIA | E12: 5 | F12: 5 | G12: 5 | H12: 9 | I12: 9 | J12: =SUM(C12:I12) -> 33 | L12: 9 | M12: 10 | N12: 10 | O12: 10 | P12: 10 | Q12: 10 | R12: 16.75 | S12: 6.75 | T12: 6.75 | X12: =SUM(L12:W12) -> 89.25 | AL12: =SUM(Z12:AK12) -> 0 | AY12: =SUM(AM12:AX12) -> 0 | BL12: =SUM(AZ12:BK12) -> 0 | BY12: =SUM(BM12:BX12) -> 0
A13: 5 | B13: HERRERA ZAPATA ELSA PIEDAD | J13: =SUM(C13:I13) -> 0 | N13: 5 | O13: 5 | P13: 5 | Q13: 5 | R13: 5 | S13: 5 | X13: =SUM(L13:W13) -> 30 | AL13: =SUM(Z13:AK13) -> 0 | AY13: =SUM(AM13:AX13) -> 0 | BL13: =SUM(AZ13:BK13) -> 0 | BY13: =SUM(BM13:BX13) -> 0
A14: 6 | B14: HERRERA HERRERA JOANA ALEXANDRA | G14: 5 | H14: 5 | I14: 9 | J14: =SUM(C14:I14) -> 19 | L14: 4 | M14: 4 | N14: 5 | O14: 5 | P14: 5 | X14: =SUM(L14:W14) -> 23 | AL14: =SUM(Z14:AK14) -> 0 | AY14: =SUM(AM14:AX14) -> 0 | BL14: =SUM(AZ14:BK14) -> 0 | BY14: =SUM(BM14:BX14) -> 0
A15: 7 | B15: MOLINA BELTRAN LUIS RAFAEL | J15: =SUM(C15:I15) -> 0 | M15: 5 | N15: 5 | O15: 5 | P15: 5 | Q15: 5 | R15: 5 | X15: =SUM(L15:W15) -> 30 | AL15: =SUM(Z15:AK15) -> 0 | AY15: =SUM(AM15:AX15) -> 0 | BL15: =SUM(AZ15:BK15) -> 0 | BY15: =SUM(BM15:BX15) -> 0
A16: 8 | B16: MONGE PRUNA JOSUE DAMIÁN | J16: =SUM(C16:I16) -> 0 | Q16: 5 | R16: 5 | S16: 5 | X16: =SUM(L16:W16) -> 15 | AL16: =SUM(Z16:AK16) -> 0 | AY16: =SUM(AM16:AX16) -> 0 | BL16: =SUM(AZ16:BK16) -> 0 | BY16: =SUM(BM16:BX16) -> 0
A17: 9 | B17: MOSCUY ALVAREZ ANTONY ALEXANDER | H17: 5 | I17: 5 | J17: =SUM(C17:I17) -> 10 | L17: 5 | M17: 5 | N17: 5 | O17: 5 | X17: =SUM(L17:W17) -> 20 | AL17: =SUM(Z17:AK17) -> 0 | AY17: =SUM(AM17:AX17) -> 0 | BL17: =SUM(AZ17:BK17) -> 0 | BY17: =SUM(BM17:BX17) -> 0
A18: 10 | B18: MOSCUY ALVAREZ MONICA AZUCENA | J18: =SUM(C18:I18) -> 0 | M18: 5 | N18: 5 | O18: 5 | X18: =SUM(L18:W18) -> 15 | AL18: =SUM(Z18:AK18) -> 0 | AY18: =SUM(AM18:AX18) -> 0 | BL18: =SUM(AZ18:BK18) -> 0 | BY18: =SUM(BM18:BX18) -> 0
A19: 11 | B19: MOSCUY CULQUI MARIA NORMA | G19: 5 | H19: 5 | I19: 5 | J19: =SUM(C19:I19) -> 15 | M19: 5 | N19: 5 | O19: 5 | P19: 5 | Q19: 5 | R19: 5 | X19: =SUM(L19:W19) -> 30 | AL19: =SUM(Z19:AK19) -> 0 | AY19: =SUM(AM19:AX19) -> 0 | BL19: =SUM(AZ19:BK19) -> 0 | BY19: =SUM(BM19:BX19) -> 0
A20: 12 | B20: MOSCUY ALVAREZ BLANCA ROCIO | F20: 5 | G20: 5 | H20: 5 | I20: 10 | J20: =SUM(C20:I20) -> 25 | L20: 10 | M20: 10 | N20: 10 | O20: 10 | P20: 10 | Q20: 10 | R20: 10 | S20: 10 | X20: =SUM(L20:W20) -> 80 | AL20: =SUM(Z20:AK20) -> 0 | AY20: =SUM(AM20:AX20) -> 0 | BL20: =SUM(AZ20:BK20) -> 0 | BY20: =SUM(BM20:BX20) -> 0
A21: 13 | B21: MOSCUY CHACON VICTOR RODOLFO | J21: =SUM(C21:I21) -> 0 | P21: 5 | Q21: 5 | R21: 5 | X21: =SUM(L21:W21) -> 15 | AL21: =SUM(Z21:AK21) -> 0 | AY21: =SUM(AM21:AX21) -> 0 | BL21: =SUM(AZ21:BK21) -> 0 | BY21: =SUM(BM21:BX21) -> 0
A22: 14 | B22: PANCHI HERRERA ANAHI ALEJANDRA | J22: =SUM(C22:I22) -> 0 | R22: 5 | S22: 5 | T22: 5 | X22: =SUM(L22:W22) -> 15 | AL22: =SUM(Z22:AK22) -> 0 | AY22: =SUM(AM22:AX22) -> 0 | BL22: =SUM(AZ22:BK22) -> 0 | BY22: =SUM(BM22:BX22) -> 0
A23: 15 | B23: PEÑAFIEL CHICAIZA CARLOS WLADIMIR | E23: 5 | F23: 5 | G23: 5 | H23: 5 | I23: 5 | J23: =SUM(C23:I23) -> 25 | L23: 5 | Q23: 10 | R23: 10 | S23: 10 | X23: =SUM(L23:W23) -> 35 | AL23: =SUM(Z23:AK23) -> 0 | AY23: =SUM(AM23:AX23) -> 0 | BL23: =SUM(AZ23:BK23) -> 0 | BY23: =SUM(BM23:BX23) -> 0
A24: 16 | B24: PEÑAFIEL CHICAIZA MAURICIO CRISTOBAL | J24: =SUM(C24:I24) -> 0 | P24: 15 | Q24: 15 | R24: 15 | X24: =SUM(L24:W24) -> 45 | AL24: =SUM(Z24:AK24) -> 0 | AY24: =SUM(AM24:AX24) -> 0 | BL24: =SUM(AZ24:BK24) -> 0 | BY24: =SUM(BM24:BX24) -> 0
A25: 17 | B25: PRUNA CANDO JUAN DAVID | J25: =SUM(C25:I25) -> 0 | Q25: 5 | R25: 5 | S25: 5 | X25: =SUM(L25:W25) -> 15 | AL25: =SUM(Z25:AK25) -> 0 | AY25: =SUM(AM25:AX25) -> 0 | BL25: =SUM(AZ25:BK25) -> 0 | BY25: =SUM(BM25:BX25) -> 0
A26: 18 | B26: PRUNA SINCHIGUANO KELLY MONSERRATH | J26: =SUM(C26:I26) -> 0 | P26: 5 | Q26: 5 | R26: 5 | X26: =SUM(L26:W26) -> 15 | AL26: =SUM(Z26:AK26) -> 0 | AY26: =SUM(AM26:AX26) -> 0 | BL26: =SUM(AZ26:BK26) -> 0 | BY26: =SUM(BM26:BX26) -> 0
A27: 19 | B27: PRUNA MOSCUY LEIDY GISSELA | J27: =SUM(C27:I27) -> 0 | P27: 5 | Q27: 5 | R27: 5 | X27: =SUM(L27:W27) -> 15 | AL27: =SUM(Z27:AK27) -> 0 | AY27: =SUM(AM27:AX27) -> 0 | BL27: =SUM(AZ27:BK27) -> 0 | BY27: =SUM(BM27:BX27) -> 0
A28: 20 | B28: PRUNA CANDO LIZARDO RAUL | J28: =SUM(C28:I28) -> 0 | L28: 10 | X28: =SUM(L28:W28) -> 10 | AL28: =SUM(Z28:AK28) -> 0 | AY28: =SUM(AM28:AX28) -> 0 | BL28: =SUM(AZ28:BK28) -> 0 | BY28: =SUM(BM28:BX28) -> 0
A29: 21 | B29: PRUNA SINCHIGUANOHEIDY NAOMI | J29: =SUM(C29:I29) -> 0 | N29: 5 | O29: 5 | P29: 5 | X29: =SUM(L29:W29) -> 15 | AL29: =SUM(Z29:AK29) -> 0 | AY29: =SUM(AM29:AX29) -> 0 | BL29: =SUM(AZ29:BK29) -> 0 | BY29: =SUM(BM29:BX29) -> 0
A30: 22 | B30: PRUNA CANDO NORMA NATALY | F30: 5 | G30: 5 | H30: 5 | I30: 5 | J30: =SUM(C30:I30) -> 20 | L30: 5 | M30: 5 | N30: 5 | O30: 5 | X30: =SUM(L30:W30) -> 20 | AL30: =SUM(Z30:AK30) -> 0 | AY30: =SUM(AM30:AX30) -> 0 | BL30: =SUM(AZ30:BK30) -> 0 | BY30: =SUM(BM30:BX30) -> 0
A31: 23 | B31: RODRIGUEZ HERRERA MIRIAM ELIZABETH | J31: =SUM(C31:I31) -> 0 | O31: 5 | P31: 5 | Q31: 5 | R31: 5 | S31: 5 | T31: 5 | X31: =SUM(L31:W31) -> 30 | AL31: =SUM(Z31:AK31) -> 0 | AY31: =SUM(AM31:AX31) -> 0 | BL31: =SUM(AZ31:BK31) -> 0 | BY31: =SUM(BM31:BX31) -> 0
A32: 24 | B32: SINCHIGUANO BASANTES VERÓNICAGISSELA | D32: 5 | E32: 5 | F32: 5 | G32: 5 | H32: 5 | I32: 5 | J32: =SUM(C32:I32) -> 30 | X32: =SUM(L32:W32) -> 0 | AL32: =SUM(Z32:AK32) -> 0 | AY32: =SUM(AM32:AX32) -> 0 | BL32: =SUM(AZ32:BK32) -> 0 | BY32: =SUM(BM32:BX32) -> 0
A33: 25 | B33: ZAPATA HERRERA ALEX DAVID | J33: =SUM(C33:I33) -> 0 | L33: 10 | M33: 10 | N33: 10 | O33: 10 | P33: 10 | Q33: 10 | R33: 10 | S33: 10 | T33: 10 | X33: =SUM(L33:W33) -> 90 | AL33: =SUM(Z33:AK33) -> 0 | AY33: =SUM(AM33:AX33) -> 0 | BL33: =SUM(AZ33:BK33) -> 0 | BY33: =SUM(BM33:BX33) -> 0
A34: TOTAL INTERÉS | D34: =SUM(D9:D33) -> 5 | E34: =SUM(E9:E33) -> 15 | F34: =SUM(F9:F33) -> 25 | G34: =SUM(G9:G33) -> 35 | H34: =SUM(H9:H33) -> 44 | I34: =SUM(I9:I33) -> 53 | J34: =SUM(D34:I34) -> 177 | L34: =SUM(L9:L33) -> 58 | M34: =SUM(M9:M33) -> 69 | N34: =SUM(N9:N33) -> 80 | O34: =SUM(O9:O33) -> 90 | P34: =SUM(P9:P33) -> 100 | Q34: =SUM(Q9:Q33) -> 110 | R34: =SUM(R9:R33) -> 121.75 | S34: =SUM(S9:S33) -> 66.75 | ... W34: =SUM(W9:W33) -> 0 | X34: =SUM(L34:W34) -> 727.25 | AY34: =SUM(AM34:AX34) -> 0 | BL34: =SUM(AZ34:BK34) -> 0
J35: =SUM(J9:J33) -> 177 | X35: =SUM(X9:X33) -> 727.25 | AL35: =SUM(AL9:AL33) -> 0 | BY35: =SUM(BY9:BY33) -> 0
AY36: =SUM(AY9:AY34) -> 0 | BL36: =SUM(BL9:BL34) -> 0
L38: TOTAL SUMA AHORRO GENERAL + INTERESES GENERAL) | M38: =1250+P36 -> 1250
J39: JULIO - ABRIL | AW39: UTILIDAD | AX39: 849.22 | AY39: 0.6
AW40: CAPITALIZACIÓN | AX40: 283.07 | AY40: 0.2
AW41: EMERGENCIA | AX41: 283.07 | AY41: 0.2
AX43: =AX39+AX40+AX41 -> 1415.36

Sheet CALCULO INTERES
A1: CAJA DE AHORRO
A3: COMUNAL
A4: VERDECOCHA
A5: Sembrando juntos para un futuro
A7: Nº | B7: SOCIO | C7: TABLA DE REPARTICION DE EXCEDENTES GRUPALES | O7: FONDO A REPARTIR | Q7: 0 | R7: SALDO NUEVO CICLO
C9: SALDOS PROMEDIO | O9: SALDO PROMEDIO | P9: % | Q9: VALOR A REPARTIR
C10: ENE | D10: FEB | E10: MAR | F10: ABR | G10: MAY | H10: JUN | I10: JUL | J10: AGO | K10: SEP | L10: OCT | M10: NOV | N10: DIC
A11: 1 | B11: =RAPA!D11 -> ALVAREZ PRUNA LUIS HERIBERTO | C11: =RAPA!H11 -> 10 | D11: =RAPA!S11 -> 15 | E11: =RAPA!AD11 -> 20 | F11: =RAPA!AN11 -> 25 | G11: =RAPA!AX11 -> 30 | H11: =RAPA!BH11 -> 35 | I11: =RAPA!BR11 -> 40 | J11: =RAPA!CB11 -> 45 | K11: =RAPA!CL11 -> 50 | L11: =RAPA!CV11 -> 55 | M11: =RAPA!DF11 -> 60 | N11: =RAPA!FZ11 -> 65 | O11: =+(C11+D11+E11+F11+G11+H11+I11+J11+K11+L11+M11+N11)/12 -> 37.5 | P11: =(O11*100%)/O$36 -> 0.04014273 | Q11: =Q$7*P11 -> 0 | R11: =RAPA!FZ11+Q11 -> 65
A12: 2 | B12: =RAPA!D12 -> CHACHAPOYA TOAPANTA RAUL GERARDO | C12: =RAPA!H12 -> 10 | D12: =RAPA!S12 -> 15 | E12: =RAPA!AD12 -> 20 | F12: =RAPA!AN12 -> 25 | G12: =RAPA!AX12 -> 30 | H12: =RAPA!BH12 -> 35 | I12: =RAPA!BR12 -> 40 | J12: =RAPA!CB12 -> 45 | K12: =RAPA!CL12 -> 50 | L12: =RAPA!CV12 -> 55 | M12: =RAPA!DF12 -> 60 | N12: =RAPA!FZ12 -> 65 | O12: =(C12+D12+E12+F12+G12+H12+I12+J12+K12+L12+M12+N12)/12 -> 37.5 | P12: =(O12*100%)/O$36 -> 0.04014273 | Q12: =Q$7*P12 -> 0 | R12: =RAPA!FZ12+Q12 -> 65
A13: 3 | B13: =RAPA!D13 -> CHICAIZA CHACON GLORIA MARINA | C13: =RAPA!H13 -> 10 | D13: =RAPA!S13 -> 15 | E13: =RAPA!AD13 -> 20 | F13: =RAPA!AN13 -> 25 | G13: =RAPA!AX13 -> 30 | H13: =RAPA!BH13 -> 35 | I13: =RAPA!BR13 -> 40 | J13: =RAPA!CB13 -> 45 | K13: =RAPA!CL13 -> 50 | L13: =RAPA!CV13 -> 55 | M13: =RAPA!DF13 -> 60 | N13: =RAPA!FZ13 -> 65 | O13: =(C13+D13+E13+F13+G13+H13+I13+J13+K13+L13+M13+N13)/12 -> 37.5 | P13: =(O13*100%)/O$36 -> 0.04014273 | Q13: =Q$7*P13 -> 0 | R13: =RAPA!FZ13+Q13 -> 65
A14: 4 | B14: =RAPA!D14 -> HERRERA ZAPATA CARMEN ALICIA | C14: =RAPA!H14 -> 10 | D14: =RAPA!S14 -> 15 | E14: =RAPA!AD14 -> 20 | F14: =RAPA!AN14 -> 25 | G14: =RAPA!AX14 -> 30 | H14: =RAPA!BH14 -> 35 | I14: =RAPA!BR14 -> 40 | J14: =RAPA!CB14 -> 45 | K14: =RAPA!CL14 -> 50 | L14: =RAPA!CV14 -> 55 | M14: =RAPA!DF14 -> 60 | N14: =RAPA!FZ14 -> 65 | O14: =(C14+D14+E14+F14+G14+H14+I14+J14+K14+L14+M14+N14)/12 -> 37.5 | P14: =(O14*100%)/O$36 -> 0.04014273 | Q14: =Q$7*P14 -> 0 | R14: =RAPA!FZ14+Q14 -> 65
A15: 5 | B15: =RAPA!D15 -> HERRERA ZAPATA ELSA PIEDAD | C15: =RAPA!H15 -> 10 | D15: =RAPA!S15 -> 15 | E15: =RAPA!AD15 -> 20 | F15: =RAPA!AN15 -> 25 | G15: =RAPA!AX15 -> 30 | H15: =RAPA!BH15 -> 35 | I15: =RAPA!BR15 -> 40 | J15: =RAPA!CB15 -> 45 | K15: =RAPA!CL15 -> 50 | L15: =RAPA!CV15 -> 55 | M15: =RAPA!DF15 -> 60 | N15: =RAPA!FZ15 -> 65 | O15: =(C15+D15+E15+F15+G15+H15+I15+J15+K15+L15+M15+N15)/12 -> 37.5 | P15: =(O15*100%)/O$36 -> 0.04014273 | Q15: =Q$7*P15 -> 0 | R15: =RAPA!FZ15+Q15 -> 65
A16: 6 | B16: =RAPA!D16 -> HERRERA HERRERA JOANA ALEXANDRA | C16: =RAPA!H16 -> 10 | D16: =RAPA!S16 -> 15 | E16: =RAPA!AD16 -> 20 | F16: =RAPA!AN16 -> 25 | G16: =RAPA!AX16 -> 30 | H16: =RAPA!BH16 -> 35 | I16: =RAPA!BR16 -> 40 | J16: =RAPA!CB16 -> 45 | K16: =RAPA!CL16 -> 50 | L16: =RAPA!CV16 -> 55 | M16: =RAPA!DF16 -> 60 | N16: =RAPA!FZ16 -> 65 | O16: =(C16+D16+E16+F16+G16+H16+I16+J16+K16+L16+M16+N16)/12 -> 37.5 | P16: =(O16*100%)/O$36 -> 0.04014273 | Q16: =Q$7*P16 -> 0 | R16: =RAPA!FZ16+Q16 -> 65
A17: 7 | B17: =RAPA!D17 -> MOLINA BELTRAN LUIS RAFAEL | C17: =RAPA!H17 -> 10 | D17: =RAPA!S17 -> 10 | E17: =RAPA!AD17 -> 10 | F17: =RAPA!AN17 -> 25 | G17: =RAPA!AX17 -> 30 | H17: =RAPA!BH17 -> 35 | I17: =RAPA!BR17 -> 40 | J17: =RAPA!CB17 -> 45 | K17: =RAPA!CL17 -> 50 | L17: =RAPA!CV17 -> 55 | M17: =RAPA!DF17 -> 60 | N17: =RAPA!FZ17 -> 65 | O17: =(C17+D17+E17+F17+G17+H17+I17+J17+K17+L17+M17+N17)/12 -> 36.25 | P17: =(O17*100%)/O$36 -> 0.038804639 | Q17: =Q$7*P17 -> 0 | R17: =RAPA!FZ17+Q17 -> 65
A18: 8 | B18: =RAPA!D18 -> MONGE PRUNA JOSUE DAMIÁN | C18: =RAPA!H18 -> 10 | D18: =RAPA!S18 -> 15 | E18: =RAPA!AD18 -> 20 | F18: =RAPA!AN18 -> 25 | G18: =RAPA!AX18 -> 30 | H18: =RAPA!BH18 -> 35 | I18: =RAPA!BR18 -> 40 | J18: =RAPA!CB18 -> 45 | K18: =RAPA!CL18 -> 50 | L18: =RAPA!CV18 -> 55 | M18: =RAPA!DF18 -> 60 | N18: =RAPA!FZ18 -> 65 | O18: =(C18+D18+E18+F18+G18+H18+I18+J18+K18+L18+M18+N18)/12 -> 37.5 | P18: =(O18*100%)/O$36 -> 0.04014273 | Q18: =Q$7*P18 -> 0 | R18: =RAPA!FZ18+Q18 -> 65
A19: 9 | B19: =RAPA!D19 -> MOSCUY ALVAREZ ANTONY ALEXANDER | C19: =RAPA!H19 -> 10 | D19: =RAPA!S19 -> 10 | E19: =RAPA!AD19 -> 20 | F19: =RAPA!AN19 -> 25 | G19: =RAPA!AX19 -> 30 | H19: =RAPA!BH19 -> 35 | I19: =RAPA!BR19 -> 40 | J19: =RAPA!CB19 -> 45 | K19: =RAPA!CL19 -> 50 | L19: =RAPA!CV19 -> 55 | M19: =RAPA!DF19 -> 60 | N19: =RAPA!FZ19 -> 65 | O19: =(C19+D19+E19+F19+G19+H19+I19+J19+K19+L19+M19+N19)/12 -> 37.083333 | P19: =(O19*100%)/O$36 -> 0.039696699 | Q19: =Q$7*P19 -> 0 | R19: =RAPA!FZ19+Q19 -> 65
A20: 10 | B20: =RAPA!D20 -> MOSCUY ALVAREZ MONICA AZUCENA | C20: =RAPA!H20 -> 10 | D20: =RAPA!S20 -> 15 | E20: =RAPA!AD20 -> 20 | F20: =RAPA!AN20 -> 25 | G20: =RAPA!AX20 -> 30 | H20: =RAPA!BH20 -> 35 | I20: =RAPA!BR20 -> 40 | J20: =RAPA!CB20 -> 45 | K20: =RAPA!CL20 -> 50 | L20: =RAPA!CV20 -> 55 | M20: =RAPA!DF20 -> 60 | N20: =RAPA!FZ20 -> 65 | O20: =(C20+D20+E20+F20+G20+H20+I20+J20+K20+L20+M20+N20)/12 -> 37.5 | P20: =(O20*100%)/O$36 -> 0.04014273 | Q20: =Q$7*P20 -> 0 | R20: =RAPA!FZ20+Q20 -> 65
A21: 11 | B21: =RAPA!D21 -> MOSCUY CULQUI MARIA NORMA | C21: =RAPA!H21 -> 10 | D21: =RAPA!S21 -> 15 | E21: =RAPA!AD21 -> 20 | F21: =RAPA!AN21 -> 25 | G21: =RAPA!AX21 -> 30 | H21: =RAPA!BH21 -> 35 | I21: =RAPA!BR21 -> 40 | J21: =RAPA!CB21 -> 45 | K21: =RAPA!CL21 -> 50 | L21: =RAPA!CV21 -> 55 | M21: =RAPA!DF21 -> 60 | N21: =RAPA!FZ21 -> 65 | O21: =(C21+D21+E21+F21+G21+H21+I21+J21+K21+L21+M21+N21)/12 -> 37.5 | P21: =(O21*100%)/O$36 -> 0.04014273 | Q21: =Q$7*P21 -> 0 | R21: =RAPA!FZ21+Q21 -> 65
A22: 12 | B22: =RAPA!D22 -> MOSCUY ALVAREZ BLANCA ROCIO | C22: =RAPA!H22 -> 10 | D22: =RAPA!S22 -> 10 | E22: =RAPA!AD22 -> 20 | F22: =RAPA!AN22 -> 25 | G22: =RAPA!AX22 -> 30 | H22: =RAPA!BH22 -> 35 | I22: =RAPA!BR22 -> 40 | J22: =RAPA!CB22 -> 45 | K22: =RAPA!CL22 -> 50 | L22: =RAPA!CV22 -> 55 | M22: =RAPA!DF22 -> 60 | N22: =RAPA!FZ22 -> 65 | O22: =(C22+D22+E22+F22+G22+H22+I22+J22+K22+L22+M22+N22)/12 -> 37.083333 | P22: =(O22*100%)/O$36 -> 0.039696699 | Q22: =Q$7*P22 -> 0 | R22: =RAPA!FZ22+Q22 -> 65
A23: 13 | B23: =RAPA!D23 -> MOSCUY CHACON VICTOR RODOLFO | C23: =RAPA!H23 -> 10 | D23: =RAPA!S23 -> 15 | E23: =RAPA!AD23 -> 20 | F23: =RAPA!AN23 -> 25 | G23: =RAPA!AX23 -> 30 | H23: =RAPA!BH23 -> 35 | I23: =RAPA!BR23 -> 40 | J23: =RAPA!CB23 -> 45 | K23: =RAPA!CL23 -> 50 | L23: =RAPA!CV23 -> 55 | M23: =RAPA!DF23 -> 60 | N23: =RAPA!FZ23 -> 65 | O23: =(C23+D23+E23+F23+G23+H23+I23+J23+K23+L23+M23+N23)/12 -> 37.5 | P23: =(O23*100%)/O$36 -> 0.04014273 | Q23: =Q$7*P23 -> 0 | R23: =RAPA!FZ23+Q23 -> 65
... A35: 25 | B35: =RAPA!D35 -> ZAPATA HERRERA ALEX DAVID | C35: =RAPA!H35 -> 10 | D35: =RAPA!S35 -> 15 | E35: =RAPA!AD35 -> 20 | F35: =RAPA!AN35 -> 25 | G35: =RAPA!AX35 -> 30 | H35: =RAPA!BH35 -> 35 | I35: =RAPA!BR35 -> 40 | J35: =RAPA!CB35 -> 45 | K35: =RAPA!CL35 -> 50 | L35: =RAPA!CV35 -> 55 | M35: =RAPA!DF35 -> 60 | N35: =RAPA!FZ35 -> 65 | O35: =(C35+D35+E35+F35+G35+H35+I35+J35+K35+L35+M35+N35)/12 -> 37.5 | P35: =(O35*100%)/O$36 -> 0.04014273 | Q35: =Q$7*P35 -> 0 | R35: =RAPA!FZ35+Q35 -> 65
B36: TOTAL | C36: =SUM(C11:C35) -> 250 | D36: =SUM(D11:D35) -> 355 | E36: =SUM(E11:E35) -> 480 | F36: =SUM(F11:F35) -> 625 | G36: =SUM(G11:G35) -> 750 | H36: =SUM(H11:H35) -> 875 | I36: =SUM(I11:I35) -> 1000 | J36: =SUM(J11:J35) -> 1125 | ... R36: =SUM(R11:R35) -> 1625
Q59: descontar de gastos de la red
R61: 2000
R62: 2000
R63: =R36+R61+R62 -> 5625

Sheet SUMA INTERES TOTAL POR SOCIO
B2: CAJA DE AHORRO
B4: COMUNAL
B5: VERDECOCHA
B6: Sembrando juntos para un futuro
B8: SUMA ITERÉS TOTAL POR SOCIO
B9: Nº | C9: SOCIOS | D9: AHORRO | E9: INTERES | F9: CRÉDITOS OTORGADOS
B10: 1 | C10: ALVAREZ PRUNA LUIS HERIBERTO | D10: =+RAPA!DF11+RAPA!FX11 -> 65 | E10: =+'INTERÈSES '!J9+'INTERÈSES '!X9+'INTERÈSES '!AL9+'INTERÈSES '!AY9+'INTERÈSES '!BL9+'INTERÈSES '!BY9 -> 15 | F10: =+RAPA!T11+RAPA!AE11+RAPA!AO11+RAPA!AY11+RAPA!BI11+RAPA!BS11+RAPA!CC11+RAPA!CM11+RAPA!CW11+RAPA!DG11+RAPA!GA11 -> 100
B11: 2 | C11: CHACHAPOYA TOAPANTA RAUL GERARDO | D11: =+RAPA!DF12+RAPA!FX12 -> 65 | E11: =+'INTERÈSES '!J10+'INTERÈSES '!X10+'INTERÈSES '!AL10+'INTERÈSES '!AY10+'INTERÈSES '!BL10+'INTERÈSES '!BY10 -> 15 | F11: =+RAPA!T12+RAPA!AE12+RAPA!AO12+RAPA!AY12+RAPA!BI12+RAPA!BS12+RAPA!CC12+RAPA!CM12+RAPA!CW12+RAPA!DG12+RAPA!GA12 -> 0
B12: 3 | C12: CHICAIZA CHACON GLORIA MARINA | D12: =+RAPA!DF13+RAPA!FX13 -> 65 | E12: =+'INTERÈSES '!J11+'INTERÈSES '!X11+'INTERÈSES '!AL11+'INTERÈSES '!AY11+'INTERÈSES '!BL11+'INTERÈSES '!BY11 -> 45 | F12: =+RAPA!T13+RAPA!AE13+RAPA!AO13+RAPA!AY13+RAPA!BI13+RAPA!BS13+RAPA!CC13+RAPA!CM13+RAPA!CW13+RAPA!DG13+RAPA!GA13 -> 300
B13: 4 | C13: HERRERA ZAPATA CARMEN ALICIA | D13: =+RAPA!DF14+RAPA!FX14 -> 65 | E13: =+'INTERÈSES '!J12+'INTERÈSES '!X12+'INTERÈSES '!AL12+'INTERÈSES '!AY12+'INTERÈSES '!BL12+'INTERÈSES '!BY12 -> 122.25 | F13: =+RAPA!T14+RAPA!AE14+RAPA!AO14+RAPA!AY14+RAPA!BI14+RAPA!BS14+RAPA!CC14+RAPA!CM14+RAPA!CW14+RAPA!DG14+RAPA!GA14 -> 680
B14: 5 | C14: HERRERA ZAPATA ELSA PIEDAD | D14: =+RAPA!DF15+RAPA!FX15 -> 65 | E14: =+'INTERÈSES '!J13+'INTERÈSES '!X13+'INTERÈSES '!AL13+'INTERÈSES '!AY13+'INTERÈSES '!BL13+'INTERÈSES '!BY13 -> 30 | F14: =+RAPA!T15+RAPA!AE15+RAPA!AO15+RAPA!AY15+RAPA!BI15+RAPA!BS15+RAPA!CC15+RAPA!CM15+RAPA!CW15+RAPA!DG15+RAPA!GA15 -> 200
B15: 6 | C15: HERRERA HERRERA JOANA ALEXANDRA | D15: =+RAPA!DF16+RAPA!FX16 -> 65 | E15: =+'INTERÈSES '!J14+'INTERÈSES '!X14+'INTERÈSES '!AL14+'INTERÈSES '!AY14+'INTERÈSES '!BL14+'INTERÈSES '!BY14 -> 42 | F15: =+RAPA!T16+RAPA!AE16+RAPA!AO16+RAPA!AY16+RAPA!BI16+RAPA!BS16+RAPA!CC16+RAPA!CM16+RAPA!CW16+RAPA!DG16+RAPA!GA16 -> 280
B16: 7 | C16: MOLINA BELTRAN LUIS RAFAEL | D16: =+RAPA!DF17+RAPA!FX17 -> 65 | E16: =+'INTERÈSES '!J15+'INTERÈSES '!X15+'INTERÈSES '!AL15+'INTERÈSES '!AY15+'INTERÈSES '!BL15+'INTERÈSES '!BY15 -> 30 | F16: =+RAPA!T17+RAPA!AE17+RAPA!AO17+RAPA!AY17+RAPA!BI17+RAPA!BS17+RAPA!CC17+RAPA!CM17+RAPA!CW17+RAPA!DG17+RAPA!GA17 -> 200
B17: 8 | C17: MONGE PRUNA JOSUE DAMIÁN | D17: =+RAPA!DF18+RAPA!FX18 -> 65 | E17: =+'INTERÈSES '!J16+'INTERÈSES '!X16+'INTERÈSES '!AL16+'INTERÈSES '!AY16+'INTERÈSES '!BL16+'INTERÈSES '!BY16 -> 15 | F17: =+RAPA!T18+RAPA!AE18+RAPA!AO18+RAPA!AY18+RAPA!BI18+RAPA!BS18+RAPA!CC18+RAPA!CM18+RAPA!CW18+RAPA!DG18+RAPA!GA18 -> 100
B18: 9 | C18: MOSCUY ALVAREZ ANTONY ALEXANDER | D18: =+RAPA!DF19+RAPA!FX19 -> 65 | E18: =+'INTERÈSES '!J17+'INTERÈSES '!X17+'INTERÈSES '!AL17+'INTERÈSES '!AY17+'INTERÈSES '!BL17+'INTERÈSES '!BY17 -> 30 | F18: =+RAPA!T19+RAPA!AE19+RAPA!AO19+RAPA!AY19+RAPA!BI19+RAPA!BS19+RAPA!CC19+RAPA!CM19+RAPA!CW19+RAPA!DG19+RAPA!GA19 -> 200
B19: 10 | C19: MOSCUY ALVAREZ MONICA AZUCENA | D19: =+RAPA!DF20+RAPA!FX20 -> 65 | E19: =+'INTERÈSES '!J18+'INTERÈSES '!X18+'INTERÈSES '!AL18+'INTERÈSES '!AY18+'INTERÈSES '!BL18+'INTERÈSES '!BY18 -> 15 | F19: =+RAPA!T20+RAPA!AE20+RAPA!AO20+RAPA!AY20+RAPA!BI20+RAPA!BS20+RAPA!CC20+RAPA!CM20+RAPA!CW20+RAPA!DG20+RAPA!GA20 -> 100
B20: 11 | C20: MOSCUY CULQUI MARIA NORMA | D20: =+RAPA!DF21+RAPA!FX21 -> 65 | E20: =+'INTERÈSES '!J19+'INTERÈSES '!X19+'INTERÈSES '!AL19+'INTERÈSES '!AY19+'INTERÈSES '!BL19+'INTERÈSES '!BY19 -> 45 | F20: =+RAPA!T21+RAPA!AE21+RAPA!AO21+RAPA!AY21+RAPA!BI21+RAPA!BS21+RAPA!CC21+RAPA!CM21+RAPA!CW21+RAPA!DG21+RAPA!GA21 -> 300
B21: 12 | C21: MOSCUY ALVAREZ BLANCA ROCIO | D21: =+RAPA!DF22+RAPA!FX22 -> 65 | E21: =+'INTERÈSES '!J20+'INTERÈSES '!X20+'INTERÈSES '!AL20+'INTERÈSES '!AY20+'INTERÈSES '!BL20+'INTERÈSES '!BY20 -> 105 | F21: =+RAPA!T22+RAPA!AE22+RAPA!AO22+RAPA!AY22+RAPA!BI22+RAPA!BS22+RAPA!CC22+RAPA!CM22+RAPA!CW22+RAPA!DG22+RAPA!GA22 -> 700
... B34: 25 | C34: ZAPATA HERRERA ALEX DAVID | D34: =+RAPA!DF35+RAPA!FX35 -> 65 | E34: =+'INTERÈSES '!J33+'INTERÈSES '!X33+'INTERÈSES '!AL33+'INTERÈSES '!AY33+'INTERÈSES '!BL33+'INTERÈSES '!BY33 -> 90 | F34: =+RAPA!T35+RAPA!AE35+RAPA!AO35+RAPA!AY35+RAPA!BI35+RAPA!BS35+RAPA!CC35+RAPA!CM35+RAPA!CW35+RAPA!DG35+RAPA!GA35 -> 400
B35: TOTAL | D35: =SUM(D10:D34) -> 1625 | E35: =SUM(E10:E34) -> 904.25 | F35: =SUM(F10:F34) -> 5460

Sheet LIBRETAS 
A2: REGISTRO INDIVIDUAL DE PAGOS Y AHORROS | H2: SOCIO | I2: ALVAREZ HERIBERTO | L2: 1
A3: NUMERO | B3: FECHA | C3: PRESTAMOS | H3: AHORROS | K3: ESTADO
C4: CONCEDIDO | D4: INTERES | E4: TOTAL ADEUDADO | F4: PAGO DE PRESTAMO + INTERES | G4: SALDO DE PRESTAMOS | H4: AHORROS | I4: RETIROS | J4: SALDO DE AHORROS
A5: 1 | B5: 45499 | E5: =C5+D5 -> 0 | G5: 0 | H5: 5 | J5: =H5 -> 5
A6: 2 | B6: 45534 | E6: =C6+D6 -> 0 | G6: =G5+E6-F6 -> 0 | H6: 5 | J6: =J5+H6-I6 -> 10
A7: 3 | B7: 45562 | E7: =C7+D7 -> 0 | G7: =G6+E7-F7 -> 0 | H7: 5 | J7: =J6+H7-I7 -> 15
A8: 4 | B8: 45589 | E8: =C8+D8 -> 0 | G8: =G7+E8-F8 -> 0 | H8: 5 | J8: =J7+H8-I8 -> 20
A9: 5 | B9: 45625 | E9: =C9+D9 -> 0 | G9: =G8+E9-F9 -> 0 | H9: 5 | J9: =J8+H9-I9 -> 25
A10: 6 | B10: 45653 | E10: =C10+D10 -> 0 | G10: =G9+E10-F10 -> 0 | H10: 5 | J10: =J9+H10-I10 -> 30
A11: 7 | B11: 45688 | E11: =C11+D11 -> 0 | G11: =G10+E11-F11 -> 0 | H11: 5 | J11: =J10+H11-I11 -> 35
A12: 8 | B12: 45691 | E12: =C12+D12 -> 0 | G12: =G11+E12-F12 -> 0 | H12: 5 | J12: =J11+H12-I12 -> 40
A13: 9 | B13: 45747 | C13: =[1]RAPA!CV6 -> 100 | D13: =[1]RAPA!CW6 -> 15 | E13: =C13+D13 -> 115 | G13: =G12+E13-F13 -> 115 | H13: 5 | J13: =J12+H13-I13 -> 45
A14: 10 | B14: 45777 | E14: =C14+D14 -> 0 | H14: 5 | J14: =J13+H14-I14 -> 50
A15: 11 | E15: =C15+D15 -> 0
H17: =SUM(H5:H16) -> 50
A19: REGISTRO INDIVIDUAL DE PAGOS Y AHORROS | H19: SOCIO | I19: CHACHAPOILLA GERARDO | L19: 2
A20: NUMERO | B20: FECHA | C20: PRESTAMOS | H20: AHORROS | K20: ESTADO
C21: CONCEDIDO | D21: INTERES | E21: TOTAL ADEUDADO | F21: PAGO DE PRESTAMO + INTERES | G21: SALDO DE PRESTAMOS | H21: AHORROS | I21: RETIROS | J21: SALDO DE AHORROS
A22: 1 | B22: 45499 | H22: 5 | J22: =H22 -> 5
A23: 2 | B23: 45534 | H23: 5 | J23: =J22+H23-I23 -> 10
A24: 3 | B24: 45562 | H24: 5 | J24: =J23+H24-I24 -> 15
A25: 4 | B25: 45589 | H25: 5 | J25: =J24+H25-I25 -> 20
A26: 5 | B26: 45625 | H26: 5 | J26: =J25+H26-I26 -> 25
A27: 6 | B27: 45653 | H27: 5 | J27: =J26+H27-I27 -> 30
A28: 7 | B28: 45688 | H28: 5 | J28: =J27+H28-I28 -> 35
A29: 8 | B29: 45691 | H29: 5 | J29: =J28+H29-I29 -> 40
A30: 9 | B30: 45747 | H30: 5 | J30: =J29+H30-I30 -> 45
A31: 10 | B31: 45777 | H31: 5 | J31: =J30+H31-I31 -> 50
A32: 11
A33: 12
H34: =SUM(H22:H33) -> 50 | I34: =SUM(I22:I31) -> 0
A36: REGISTRO INDIVIDUAL DE PAGOS Y AHORROS | H36: SOCIA | I36: CHICAIZA MARINA | L36: 3
A37: NUMERO | B37: FECHA | C37: PRESTAMOS | H37: AHORROS
C38: CONCEDIDO | D38: INTERES | E38: TOTAL ADEUDADO | F38: PAGO DE PRESTAMO + INTERES | G38: SALDO DE PRESTAMOS | H38: AHORROS | I38: RETIROS | J38: SALDO DE AHORROS | K38: ESTADO
A39: 1 | B39: 45499 | E39: =C39+D39 -> 0 | G39: 0 | H39: 5 | J39: =H39 -> 5
A40: 2 | B40: 45534 | E40: =C40+D40 -> 0 | G40: =G39+E40-F40 -> 0 | H40: 5 | J40: =J39+H40-I40 -> 10
A41: 3 | B41: 45562 | E41: =C41+D41 -> 0 | G41: =G40+E41-F41 -> 0 | H41: 5 | J41: =J40+H41-I41 -> 15
A42: 4 | B42: 45589 | E42: =C42+D42 -> 0 | G42: =G41+E42-F42 -> 0 | H42: 5 | J42: =J41+H42-I42 -> 20
A43: 5 | B43: 45625 | E43: =C43+D43 -> 0 | G43: =G42+E43-F43 -> 0 | H43: 5 | J43: =J42+H43-I43 -> 25
A44: 6 | B44: 45653 | E44: =C44+D44 -> 0 | G44: =G43+E44-F44 -> 0 | H44: 5 | J44: =J43+H44-I44 -> 30
A45: 7 | B45: 45688 | C45: 200 | D45: 30 | E45: =C45+D45 -> 230 | G45: =G44+E45-F45 -> 230 | H45: 5 | J45: =J44+H45-I45 -> 35
A46: 8 | B46: 45691 | E46: =C46+D46 -> 0 | F46: 10 | G46: =G45+E46-F46 -> 220 | H46: 5 | J46: =J45+H46-I46 -> 40
A47: 9 | B47: 45747 | E47: =C47+D47 -> 0 | F47: 10 | G47: =G46+E47-F47 -> 210 | H47: 5 | J47: =J46+H47-I47 -> 45
A48: 10 | B48: 45777 | C48: 100 | D48: 15 | E48: =C48+D48 -> 115 | F48: 210 | G48: =G47+E48-F48 -> 115 | H48: 5 | J48: =J47+H48-I48 -> 50
A49: 11
A50: 12
H51: =SUM(H39:H50) -> 50 | I51: =I39+I41 -> 0
A53: REGISTRO INDIVIDUAL DE PAGOS Y AHORROS | H53: SOCIA | I53: HERREA CARMEN | L53: 4
A54: NUMERO | B54: FECHA | C54: PRESTAMOS | H54: AHORROS
C55: CONCEDIDO | D55: INTERES | E55: TOTAL ADEUDADO | F55: PAGO DE PRESTAMO + INTERES | G55: SALDO DE PRESTAMOS | H55: AHORROS | I55: RETIROS | J55: SALDO DE AHORROS | K55: ESTADO
A56: 1 | B56: 45499 | C56: 100 | D56: 15 | E56: =+C56+D56 -> 115 | G56: =E56 -> 115 | H56: 5 | J56: =+H56 -> 5
A57: 2 | B57: 45534 | E57: =+C57+D57 -> 0 | F57: 5 | G57: =G56+E57-F57 -> 110 | H57: 5 | J57: =J56+H57-I57 -> 10
A58: 3 | B58: 45562 | E58: =+C58+D58 -> 0 | F58: 5 | G58: =G57+E58-F58 -> 105 | H58: 5 | J58: =J57+H58-I58 -> 15
A59: 4 | B59: 45589 | C59: 180 | D59: 27 | E59: =+C59+D59 -> 207 | F59: 105 | G59: =G58+E59-F59 -> 207 | H59: 5 | J59: =J58+H59-I59 -> 20 | K59: PAGADO
A60: 5 | B60: 45625 | E60: =+C60+D60 -> 0 | F60: 9 | G60: =G59+E60-F60 -> 198 | H60: 5 | J60: =J59+H60-I60 -> 25
A61: 6 | B61: 45653 | E61: =+C61+D61 -> 0 | F61: 9 | G61: =G60+E61-F61 -> 189 | H61: 5 | J61: =J60+H61-I61 -> 30
A62: 7 | B62: 45688 | C62: 200 | D62: 30 | E62: =+C62+D62 -> 230 | F62: 189 | G62: =G61+E62-F62 -> 230 | H62: 5 | J62: =J61+H62-I62 -> 35 | K62: PAGADO
A63: 8 | B63: 45691 | E63: =+C63+D63 -> 0 | F63: 10 | G63: =G62+E63-F63 -> 220 | H63: 5 | J63: =J62+H63-I63 -> 40
A64: 9 | B64: 45747 | E64: =+C64+D64 -> 0 | F64: 10 | G64: =G63+E64-F64 -> 210 | H64: 5 | J64: =J63+H64-I64 -> 45
A65: 10 | B65: 45777 | C65: 200 | D65: 30 | E65: =+C65+D65 -> 230 | F65: 210 | G65: =G64+E65-F65 -> 230 | H65: 5 | J65: =J64+H65-I65 -> 50 | K65: PAGADO
A66: 11
A67: 12
H68: =SUM(H56:H67) -> 50 | I68: =I58+I60 -> 0
A70: REGISTRO INDIVIDUAL DE PAGOS Y AHORROS | H70: SOCIA | I70: HERREA ELSA | L70: 5
A71: NUMERO | B71: FECHA | C71: PRESTAMOS | H71: AHORROS
C72: CONCEDIDO | D72: INTERES | E72: TOTAL ADEUDADO | F72: PAGO DE PRESTAMO + INTERES | G72: SALDO DE PRESTAMOS | H72: AHORROS | I72: RETIROS | J72: SALDO DE AHORROS | K72: ESTADO
A73: 1 | B73: 45499 | E73: =C73+D73 -> 0 | G73: 0 | H73: 5 | J73: =+H73 -> 5
A74: 2 | B74: 45534 | E74: =C74+D74 -> 0 | G74: =G73+E74-F74 -> 0 | H74: 5 | J74: =J73-I74+H74 -> 10
A75: 3 | B75: 45562 | E75: =C75+D75 -> 0 | G75: =G74+E75-F75 -> 0 | H75: 5 | J75: =J74-I75+H75 -> 15
A76: 4 | B76: 45589 | E76: =C76+D76 -> 0 | G76: =G75+E76-F76 -> 0 | H76: 5 | J76: =J75-I76+H76 -> 20
A77: 5 | B77: 45625 | E77: =C77+D77 -> 0 | G77: =G76+E77-F77 -> 0 | H77: 5 | J77: =J76-I77+H77 -> 25
A78: 6 | B78: 45653 | E78: =C78+D78 -> 0 | G78: =G77+E78-F78 -> 0 | H78: 5 | J78: =J77-I78+H78 -> 30
A79: 7 | B79: 45688 | E79: =C79+D79 -> 0 | G79: =G78+E79-F79 -> 0 | H79: 5 | J79: =J78-I79+H79 -> 35
A80: 8 | B80: 45691 | C80: 100 | D80: 15 | E80: =C80+D80 -> 115 | G80: =G79+E80-F80 -> 115 | H80: 5 | J80: =J79-I80+H80 -> 40
A81: 9 | B81: 45747 | E81: =C81+D81 -> 0 | F81: 5 | G81: =G80+E81-F81 -> 110 | H81: 5 | J81: =J80-I81+H81 -> 45
A82: 10 | B82: 45777 | E82: =C82+D82 -> 0 | F82: 5 | G82: =G81+E82-F82 -> 105 | H82: 5 | J82: =J81-I82+H82 -> 50
A83: 11
A84: 12
H85: =SUM(H73:H84) -> 50 | I85: =SUM(I73:I84) -> 0
A87: REGISTRO INDIVIDUAL DE PAGOS Y AHORROS | H87: SOCIO | I87: HERREA JOANA | L87: 6
A88: NUMERO | B88: FECHA | C88: PRESTAMOS | H88: AHORROS
C89: CONCEDIDO | D89: INTERES | E89: TOTAL ADEUDADO | F89: PAGO DE PRESTAMO + INTERES | G89: SALDO DE PRESTAMOS | H89: AHORROS | I89: RETIROS | J89: SALDO DE AHORROS | K89: ESTADO
A90: 1 | B90: 45499 | E90: =+C90+D90 -> 0 | H90: 5 | J90: =+H90 -> 5
A91: 2 | B91: 45534 | E91: =+C91+D91 -> 0 | G91: =G90+E91-F91 -> 0 | H91: 5 | J91: =J90+H91-I91 -> 10
A92: 3 | B92: 45562 | C92: 100 | D92: 15 | E92: =+C92+D92 -> 115 | G92: =G91+E92-F92 -> 115 | H92: 5 | J92: =J91+H92-I92 -> 15
A93: 4 | B93: 45589 | E93: =+C93+D93 -> 0 | F93: 5 | G93: =G92+E93-F93 -> 110 | H93: 5 | J93: =J92+H93-I93 -> 20
A94: 5 | B94: 45625 | E94: =+C94+D94 -> 0 | F94: 5 | G94: =G93+E94-F94 -> 105 | H94: 5 | J94: =J93+H94-I94 -> 25
A95: 6 | B95: 45653 | C95: 80 | D95: 12 | E95: =+C95+D95 -> 92 | F95: 105 | G95: =G94+E95-F95 -> 92 | H95: 5 | J95: =J94+H95-I95 -> 30
A96: 7 | B96: 45688 | E96: =+C96+D96 -> 0 | F96: 4 | G96: =G95+E96-F96 -> 88 | H96: 5 | J96: =J95+H96-I96 -> 35
A97: 8 | B97: 45691 | E97: =+C97+D97 -> 0 | F97: 4 | G97: =G96+E97-F97 -> 84 | H97: 5 | J97: =J96+H97-I97 -> 40
A98: 9 | B98: 45747 | C98: 100 | D98: 15 | E98: =+C98+D98 -> 115 | F98: 84 | G98: =G97+E98-F98 -> 115 | H98: 5 | J98: =J97+H98-I98 -> 45
A99: 10 | B99: 45777 | E99: =+C99+D99 -> 0 | F99: 5 | G99: =G98+E99-F99 -> 110 | H99: 5 | J99: =J98+H99-I99 -> 50
A100: 11
A101: 12
H102: =SUM(H90:H101) -> 50 | I102: =SUM(I90:I101) -> 0
A104: REGISTRO INDIVIDUAL DE PAGOS Y AHORROS | H104: SOCIO | I104: MOLINA RAFAEL | L104: 7
A105: NUMERO | B105: FECHA | C105: PRESTAMOS | H105: AHORROS
C106: CONCEDIDO | D106: INTERES | E106: TOTAL ADEUDADO | F106: PAGO DE PRESTAMO + INTERES | G106: SALDO DE PRESTAMOS | H106: AHORROS | I106: RETIROS | J106: SALDO DE AHORROS | K106: ESTADO
A107: 1 | B107: 45499 | E107: =+C107+D107 -> 0 | G107: 0 | J107: =+H107 -> 0
A108: 2 | B108: 45534 | E108: =+C108+D108 -> 0 | G108: =G107+E108-F108 -> 0 | J108: =J107+H108-I108 -> 0
...
